<Table>
<Row><Cell>cfnm_ac3mansr</Cell><Cell>Scotland A. Rodriguez</Cell><Cell>Scotland A. Rodriguez</Cell></Row>
<Row><Cell>cfnm_aelsberg1970</Cell><Cell>Alexander carl elsberg</Cell><Cell>Alexander carl elsberg</Cell></Row>
<Row><Cell>cfnm_alex_d83</Cell><Cell>Alexander Diesch</Cell><Cell>Alexander Diesch</Cell></Row>
<Row><Cell>cfnm_altariss</Cell><Cell>Martin Košťál</Cell><Cell>Martin Košťál</Cell></Row>
<Row><Cell>cfnm_amano</Cell><Cell>Ahnen Christian - Brother of Nod - Scourge of the BAALI</Cell><Cell>Ahnen Christian - Brother of Nod - Scourge of the BAALI</Cell></Row>
<Row><Cell>cfnm_amaunator</Cell><Cell>Ernst Schori</Cell><Cell>Ernst Schori</Cell></Row>
<Row><Cell>cfnm_andaj</Cell><Cell>Alexander Justus</Cell><Cell>Alexander Justus</Cell></Row>
<Row><Cell>cfnm_aoua</Cell><Cell>Falco Aulitzky</Cell><Cell>Falco Aulitzky</Cell></Row>
<Row><Cell>cfnm_apocalypse_koa</Cell><Cell>"Magic" Mike S. Khamphoukeo</Cell><Cell>"Magic" Mike S. Khamphoukeo</Cell></Row>
<Row><Cell>cfnm_aramanthius</Cell><Cell>Aramanthius</Cell><Cell>Aramanthius</Cell></Row>
<Row><Cell>cfnm_ardagast</Cell><Cell>Petr</Cell><Cell>Petr</Cell></Row>
<Row><Cell>cfnm_aretheus</Cell><Cell>Carsten Pape</Cell><Cell>Carsten Pape</Cell></Row>
<Row><Cell>cfnm_argaladir</Cell><Cell>Argaladir Elthalion</Cell><Cell>Argaladir Elthalion</Cell></Row>
<Row><Cell>cfnm_arkenus</Cell><Cell>Alexis Huang</Cell><Cell>Alexis Huang</Cell></Row>
<Row><Cell>cfnm_arleeya</Cell><Cell>Arleeya</Cell><Cell>Arleeya</Cell></Row>
<Row><Cell>cfnm_armorial</Cell><Cell>Harri Holmström</Cell><Cell>Harri Holmström</Cell></Row>
<Row><Cell>cfnm_artalencar</Cell><Cell>Arthur Alencar</Cell><Cell>Arthur Alencar</Cell></Row>
<Row><Cell>cfnm_asbo</Cell><Cell>Asbo</Cell><Cell>Asbo</Cell></Row>
<Row><Cell>cfnm_aslyn</Cell><Cell>Audrey S. L. Quay</Cell><Cell>Audrey S. L. Quay</Cell></Row>
<Row><Cell>cfnm_azalus</Cell><Cell>Azalus</Cell><Cell>Azalus</Cell></Row>
<Row><Cell>cfnm_b0ink</Cell><Cell>William Hovik</Cell><Cell>William Hovik</Cell></Row>
<Row><Cell>cfnm_balex</Cell><Cell>Alexander Löw</Cell><Cell>Alexander Löw</Cell></Row>
<Row><Cell>cfnm_balianofibelin</Cell><Cell>Ian Williams</Cell><Cell>Ian Williams</Cell></Row>
<Row><Cell>cfnm_balin</Cell><Cell>R.C. Godejord</Cell><Cell>R.C. Godejord</Cell></Row>
<Row><Cell>cfnm_baranduin75</Cell><Cell>Stefan H.</Cell><Cell>Stefan H.</Cell></Row>
<Row><Cell>cfnm_barbante</Cell><Cell>Stiven conte</Cell><Cell>Stiven conte</Cell></Row>
<Row><Cell>cfnm_baumhauer</Cell><Cell>Albert Baumhauer</Cell><Cell>Albert Baumhauer</Cell></Row>
<Row><Cell>cfnm_bdsxjack</Cell><Cell>JACK KROSS</Cell><Cell>JACK KROSS</Cell></Row>
<Row><Cell>cfnm_beastington</Cell><Cell>Aaron Charles Hussey</Cell><Cell>Aaron Charles Hussey</Cell></Row>
<Row><Cell>cfnm_bendubai</Cell><Cell>Bendubai</Cell><Cell>Bendubai</Cell></Row>
<Row><Cell>cfnm_biefstuk</Cell><Cell>Biefstuk</Cell><Cell>Biefstuk</Cell></Row>
<Row><Cell>cfnm_bigiissxrx</Cell><Cell>Bjoern Horn</Cell><Cell>Bjoern Horn</Cell></Row>
<Row><Cell>cfnm_bionicfemme</Cell><Cell>Esther Zinn</Cell><Cell>Esther Zinn</Cell></Row>
<Row><Cell>cfnm_blahn</Cell><Cell>Benjamin von Lahn</Cell><Cell>Benjamin von Lahn</Cell></Row>
<Row><Cell>cfnm_blakstar</Cell><Cell>jan steinar stuvik</Cell><Cell>jan steinar stuvik</Cell></Row>
<Row><Cell>cfnm_blomman</Cell><Cell>Alexander Blomquist</Cell><Cell>Alexander Blomquist</Cell></Row>
<Row><Cell>cfnm_borbi01</Cell><Cell>Borbi01</Cell><Cell>Borbi02</Cell></Row>
<Row><Cell>cfnm_boston</Cell><Cell>Brian Tartell</Cell><Cell>Brian Tartell</Cell></Row>
<Row><Cell>cfnm_bretzer</Cell><Cell>Joseph Bretzer</Cell><Cell>Joseph Bretzer</Cell></Row>
<Row><Cell>cfnm_buddy53189</Cell><Cell>Buddy53189</Cell><Cell>Buddy53190</Cell></Row>
<Row><Cell>cfnm_bunnyhunt80</Cell><Cell>Bunnyhunt80</Cell><Cell>Bunnyhunt81</Cell></Row>
<Row><Cell>cfnm_bydevoi</Cell><Cell>Peter Khristenko</Cell><Cell>Peter Khristenko</Cell></Row>
<Row><Cell>cfnm_caesar5285</Cell><Cell>Laurence Stratton</Cell><Cell>Laurence Stratton</Cell></Row>
<Row><Cell>cfnm_caleb100</Cell><Cell>ToMáš prokop</Cell><Cell>ToMáš prokop</Cell></Row>
<Row><Cell>cfnm_capra</Cell><Cell>Pascal Fritschi</Cell><Cell>Pascal Fritschi</Cell></Row>
<Row><Cell>cfnm_cavetree</Cell><Cell>Marek Staroň</Cell><Cell>Marek Staroň</Cell></Row>
<Row><Cell>cfnm_cavjo</Cell><Cell>Cavjo</Cell><Cell>Cavjo</Cell></Row>
<Row><Cell>cfnm_cbello57</Cell><Cell>Christopher James Bellot</Cell><Cell>Christopher James Bellot</Cell></Row>
<Row><Cell>cfnm_cerberus</Cell><Cell>Jörg Schulze</Cell><Cell>Jörg Schulze</Cell></Row>
<Row><Cell>cfnm_cian</Cell><Cell>Cian</Cell><Cell>Cian</Cell></Row>
<Row><Cell>cfnm_citizendog</Cell><Cell>Citizen Dog</Cell><Cell>Citizen Dog</Cell></Row>
<Row><Cell>cfnm_cmd865</Cell><Cell>Connor Dare</Cell><Cell>Connor Dare</Cell></Row>
<Row><Cell>cfnm_cocik</Cell><Cell>Lukáš Codr</Cell><Cell>Lukáš Codr</Cell></Row>
<Row><Cell>cfnm_codepanda</Cell><Cell>André Lønvik</Cell><Cell>André Lønvik</Cell></Row>
<Row><Cell>cfnm_coigreach</Cell><Cell>Tuomas Joukonpoika</Cell><Cell>Tuomas Joukonpoika</Cell></Row>
<Row><Cell>cfnm_cool_paulchen</Cell><Cell>Sebastian Lange</Cell><Cell>Sebastian Lange</Cell></Row>
<Row><Cell>cfnm_cooltoon22</Cell><Cell>Yannick Perotti</Cell><Cell>Yannick Perotti</Cell></Row>
<Row><Cell>cfnm_corlif</Cell><Cell>Corlif</Cell><Cell>Corlif</Cell></Row>
<Row><Cell>cfnm_croberts68</Cell><Cell>Chris Roberts</Cell><Cell>Chris Roberts</Cell></Row>
<Row><Cell>cfnm_crozan</Cell><Cell>Thomas Cronin</Cell><Cell>Thomas Cronin</Cell></Row>
<Row><Cell>cfnm_d_elgin</Cell><Cell>William</Cell><Cell>William</Cell></Row>
<Row><Cell>cfnm_daaubrey</Cell><Cell>Aubrey D. Atkinson</Cell><Cell>Aubrey D. Atkinson</Cell></Row>
<Row><Cell>cfnm_dafritz</Cell><Cell>Stefan Seifried</Cell><Cell>Stefan Seifried</Cell></Row>
<Row><Cell>cfnm_danners</Cell><Cell>Danervator</Cell><Cell>Danervator</Cell></Row>
<Row><Cell>cfnm_darkling</Cell><Cell>Anthony</Cell><Cell>Anthony</Cell></Row>
<Row><Cell>cfnm_darkstar</Cell><Cell>Kevin Mitchell</Cell><Cell>Kevin Mitchell</Cell></Row>
<Row><Cell>cfnm_darkwc</Cell><Cell>Dark</Cell><Cell>Dark</Cell></Row>
<Row><Cell>cfnm_darlandra</Cell><Cell>Christopher Thomas Parker</Cell><Cell>Christopher Thomas Parker</Cell></Row>
<Row><Cell>cfnm_darthanhaj</Cell><Cell>Frank j. Flury</Cell><Cell>Frank j. Flury</Cell></Row>
<Row><Cell>cfnm_dartknight</Cell><Cell>Alexandra Partipilo</Cell><Cell>Alexandra Partipilo</Cell></Row>
<Row><Cell>cfnm_darwin</Cell><Cell>Antonin Hildebrand</Cell><Cell>Antonin Hildebrand</Cell></Row>
<Row><Cell>cfnm_dasmonoid</Cell><Cell>DasMonoid</Cell><Cell>DasMonoid</Cell></Row>
<Row><Cell>cfnm_davaduff</Cell><Cell>David</Cell><Cell>David</Cell></Row>
<Row><Cell>cfnm_derfranke</Cell><Cell>Justus Präg</Cell><Cell>Justus Präg</Cell></Row>
<Row><Cell>cfnm_desax</Cell><Cell>Thomas Hofmann</Cell><Cell>Thomas Hofmann</Cell></Row>
<Row><Cell>cfnm_desol</Cell><Cell>Jeffrey LeVeque</Cell><Cell>Jeffrey LeVeque</Cell></Row>
<Row><Cell>cfnm_devfern93</Cell><Cell>Devin Fernandez</Cell><Cell>Devin Fernandez</Cell></Row>
<Row><Cell>cfnm_diodotus</Cell><Cell>Thomas Henry Joseph Douglas Ayers</Cell><Cell>Thomas Henry Joseph Douglas Ayers</Cell></Row>
<Row><Cell>cfnm_doctorbecker</Cell><Cell>Wilhelm von Beck</Cell><Cell>Wilhelm von Beck</Cell></Row>
<Row><Cell>cfnm_doddosk</Cell><Cell>Jozef</Cell><Cell>Jozef</Cell></Row>
<Row><Cell>cfnm_dogfoodjoe</Cell><Cell>Dogfoodjoe</Cell><Cell>Dogfoodjoe</Cell></Row>
<Row><Cell>cfnm_donesteban</Cell><Cell>Don Esteban</Cell><Cell>Don Esteban</Cell></Row>
<Row><Cell>cfnm_duxdanny</Cell><Cell>Daniel Mazur</Cell><Cell>Daniel Mazur</Cell></Row>
<Row><Cell>cfnm_eastbayrae</Cell><Cell>Eastbayrae</Cell><Cell>Eastbayrae</Cell></Row>
<Row><Cell>cfnm_eastbishop</Cell><Cell>Leonard "Bishop" Bleasdale</Cell><Cell>Leonard "Bishop" Bleasdale</Cell></Row>
<Row><Cell>cfnm_edara</Cell><Cell>Joshua Bare</Cell><Cell>Joshua Bare</Cell></Row>
<Row><Cell>cfnm_eirik</Cell><Cell>Erik Kupferer</Cell><Cell>Erik Kupferer</Cell></Row>
<Row><Cell>cfnm_englands_own</Cell><Cell>Paul Kinder</Cell><Cell>Paul Kinder</Cell></Row>
<Row><Cell>cfnm_eopblogs</Cell><Cell>Edward Oliver Killigrew Penrose Esq</Cell><Cell>Edward Oliver Killigrew Penrose Esq</Cell></Row>
<Row><Cell>cfnm_escwald</Cell><Cell>Erik Karlsson</Cell><Cell>Erik Karlsson</Cell></Row>
<Row><Cell>cfnm_etegaem</Cell><Cell>Etegaem</Cell><Cell>Etegaem</Cell></Row>
<Row><Cell>cfnm_eyn</Cell><Cell>benjamin ward</Cell><Cell>benjamin ward</Cell></Row>
<Row><Cell>cfnm_faldi</Cell><Cell>Pascal Grob</Cell><Cell>Pascal Grob</Cell></Row>
<Row><Cell>cfnm_farleyman</Cell><Cell>Steven Rash</Cell><Cell>Steven Rash</Cell></Row>
<Row><Cell>cfnm_favorlock</Cell><Cell>Evan Dane Lindsay</Cell><Cell>Evan Dane Lindsay</Cell></Row>
<Row><Cell>cfnm_felixg</Cell><Cell>Felix Grünewald</Cell><Cell>Felix Grünewald</Cell></Row>
<Row><Cell>cfnm_filcat</Cell><Cell>Felices Veterator a parvulo</Cell><Cell>Felices Veterator a parvulo</Cell></Row>
<Row><Cell>cfnm_flanker27</Cell><Cell>Flanker</Cell><Cell>Flanker</Cell></Row>
<Row><Cell>cfnm_flashfire</Cell><Cell>James Venes</Cell><Cell>James Venes</Cell></Row>
<Row><Cell>cfnm_flo0220</Cell><Cell>Florian</Cell><Cell>Florian</Cell></Row>
<Row><Cell>cfnm_forsix</Cell><Cell>Forsix</Cell><Cell>Forsix</Cell></Row>
<Row><Cell>cfnm_forthe</Cell><Cell>Long</Cell><Cell>Long</Cell></Row>
<Row><Cell>cfnm_francmg</Cell><Cell>Franz von Neudek</Cell><Cell>Franz von Neudek</Cell></Row>
<Row><Cell>cfnm_freek81294</Cell><Cell>Freek81294</Cell><Cell>Freek81295</Cell></Row>
<Row><Cell>cfnm_garbaldie</Cell><Cell>garett gaudet</Cell><Cell>garett gaudet</Cell></Row>
<Row><Cell>cfnm_gatlish</Cell><Cell>Daichi Shinohara</Cell><Cell>Daichi Shinohara</Cell></Row>
<Row><Cell>cfnm_gauloises30</Cell><Cell>Rose Benjamin</Cell><Cell>Rose Benjamin</Cell></Row>
<Row><Cell>cfnm_genshed62</Cell><Cell>Marvin A Crews</Cell><Cell>Marvin A Crews</Cell></Row>
<Row><Cell>cfnm_george</Cell><Cell>Georg Suppan</Cell><Cell>Georg Suppan</Cell></Row>
<Row><Cell>cfnm_ghostleviathan</Cell><Cell>Troy M Rubert</Cell><Cell>Troy M Rubert</Cell></Row>
<Row><Cell>cfnm_gidister</Cell><Cell>Lisa Engel</Cell><Cell>Lisa Engel</Cell></Row>
<Row><Cell>cfnm_gilic</Cell><Cell>Sebastian "gilic" Wienhold</Cell><Cell>Sebastian "gilic" Wienhold</Cell></Row>
<Row><Cell>cfnm_gizmotin</Cell><Cell>Simo</Cell><Cell>Simo</Cell></Row>
<Row><Cell>cfnm_godofwar889</Cell><Cell>Giuseppe DeGaetano </Cell><Cell>Giuseppe DeGaetano </Cell></Row>
<Row><Cell>cfnm_goober</Cell><Cell>Peterka I</Cell><Cell>Peterka I</Cell></Row>
<Row><Cell>cfnm_gorkafatchi</Cell><Cell>fatchi</Cell><Cell>fatchi</Cell></Row>
<Row><Cell>cfnm_gorrrrrr</Cell><Cell>Gorrrrrr</Cell><Cell>Gorrrrrr</Cell></Row>
<Row><Cell>cfnm_gosuwall</Cell><Cell>GoSuWaLL</Cell><Cell>GoSuWaLL</Cell></Row>
<Row><Cell>cfnm_greiger</Cell><Cell>Ryan McAuley</Cell><Cell>Ryan McAuley</Cell></Row>
<Row><Cell>cfnm_grievous544</Cell><Cell>Grievous544</Cell><Cell>Grievous545</Cell></Row>
<Row><Cell>cfnm_grip</Cell><Cell>Stefan Botond</Cell><Cell>Stefan Botond</Cell></Row>
<Row><Cell>cfnm_gripman</Cell><Cell>Marek Macháček</Cell><Cell>Marek Macháček</Cell></Row>
<Row><Cell>cfnm_grndmstr1337</Cell><Cell>Robert </Cell><Cell>Robert </Cell></Row>
<Row><Cell>cfnm_gronkh</Cell><Cell>Gronkh</Cell><Cell>Gronkh</Cell></Row>
<Row><Cell>cfnm_guemsterk</Cell><Cell>Guemsterk</Cell><Cell>Guemsterk</Cell></Row>
<Row><Cell>cfnm_gummiente</Cell><Cell>Andreas Aistleitner</Cell><Cell>Andreas Aistleitner</Cell></Row>
<Row><Cell>cfnm_gumonleg</Cell><Cell>James</Cell><Cell>James</Cell></Row>
<Row><Cell>cfnm_gunibaer</Cell><Cell>Marc Elxnat</Cell><Cell>Marc Elxnat</Cell></Row>
<Row><Cell>cfnm_gurupl</Cell><Cell>Sir Adam Baron of Poland</Cell><Cell>Sir Adam Baron of Poland</Cell></Row>
<Row><Cell>cfnm_hakase</Cell><Cell>Crest Lwin</Cell><Cell>Crest Lwin</Cell></Row>
<Row><Cell>cfnm_haraldth</Cell><Cell>Peter Mattsson</Cell><Cell>Peter Mattsson</Cell></Row>
<Row><Cell>cfnm_hasgaroth</Cell><Cell>David Nieß</Cell><Cell>David Nieß</Cell></Row>
<Row><Cell>cfnm_haskald</Cell><Cell>Craig Jensen</Cell><Cell>Craig Jensen</Cell></Row>
<Row><Cell>cfnm_heathen</Cell><Cell>Christopher Fournier</Cell><Cell>Christopher Fournier</Cell></Row>
<Row><Cell>cfnm_helmersen</Cell><Cell>Andreas Bjørnbekk</Cell><Cell>Andreas Bjørnbekk</Cell></Row>
<Row><Cell>cfnm_henkins</Cell><Cell>Kristoffer Bjånesø</Cell><Cell>Kristoffer Bjånesø</Cell></Row>
<Row><Cell>cfnm_herko_ter_horst</Cell><Cell>Herko ter Horst</Cell><Cell>Herko ter Horst</Cell></Row>
<Row><Cell>cfnm_heroicbbq</Cell><Cell>James</Cell><Cell>James</Cell></Row>
<Row><Cell>cfnm_highlake</Cell><Cell>Henrik Jarman Topsoe</Cell><Cell>Henrik Jarman Topsoe</Cell></Row>
<Row><Cell>cfnm_holymittens</Cell><Cell>John Paul Kastronis III</Cell><Cell>John Paul Kastronis III</Cell></Row>
<Row><Cell>cfnm_honzimus</Cell><Cell>Jan Krejčí</Cell><Cell>Jan Krejčí</Cell></Row>
<Row><Cell>cfnm_horton</Cell><Cell>Thomas Marsh</Cell><Cell>Thomas Marsh</Cell></Row>
<Row><Cell>cfnm_howard</Cell><Cell>Antoine SOL</Cell><Cell>Antoine SOL</Cell></Row>
<Row><Cell>cfnm_hugebull</Cell><Cell>Hugebull</Cell><Cell>Hugebull</Cell></Row>
<Row><Cell>cfnm_hunter</Cell><Cell>Joseph Rolfe</Cell><Cell>Joseph Rolfe</Cell></Row>
<Row><Cell>cfnm_hyperious</Cell><Cell>Gordon Huang</Cell><Cell>Gordon Huang</Cell></Row>
<Row><Cell>cfnm_cheezey_bites</Cell><Cell>James Thompson</Cell><Cell>James Thompson</Cell></Row>
<Row><Cell>cfnm_i3lade</Cell><Cell>Phuc Tran</Cell><Cell>Phuc Tran</Cell></Row>
<Row><Cell>cfnm_iakhovas</Cell><Cell>Iakhovas</Cell><Cell>Iakhovas</Cell></Row>
<Row><Cell>cfnm_iamhowie</Cell><Cell>Peanutmojo</Cell><Cell>Peanutmojo</Cell></Row>
<Row><Cell>cfnm_idcrusher</Cell><Cell>ID Crusher</Cell><Cell>ID Crusher</Cell></Row>
<Row><Cell>cfnm_ikantspeell</Cell><Cell>Ikantspeell</Cell><Cell>Ikantspeell</Cell></Row>
<Row><Cell>cfnm_ilevus</Cell><Cell>Veli Donmez</Cell><Cell>Veli Donmez</Cell></Row>
<Row><Cell>cfnm_illathid</Cell><Cell>Erik Olmstead</Cell><Cell>Erik Olmstead</Cell></Row>
<Row><Cell>cfnm_immik</Cell><Cell>Roman Ryabov</Cell><Cell>Roman Ryabov</Cell></Row>
<Row><Cell>cfnm_indoc</Cell><Cell>Filip Sandström</Cell><Cell>Filip Sandström</Cell></Row>
<Row><Cell>cfnm_insaneberg</Cell><Cell>From Stefan for  Loliya Harry</Cell><Cell>From Stefan for  Loliya Harry</Cell></Row>
<Row><Cell>cfnm_inter0</Cell><Cell>Inter</Cell><Cell>Inter</Cell></Row>
<Row><Cell>cfnm_invisibleshadow</Cell><Cell>Timothy</Cell><Cell>Timothy</Cell></Row>
<Row><Cell>cfnm_iolalog</Cell><Cell>Olav Lognvik</Cell><Cell>Olav Lognvik</Cell></Row>
<Row><Cell>cfnm_isi</Cell><Cell>ISI</Cell><Cell>ISI</Cell></Row>
<Row><Cell>cfnm_ithrud</Cell><Cell>Mark Berry</Cell><Cell>Mark Berry</Cell></Row>
<Row><Cell>cfnm_j4ck</Cell><Cell>Jakub Mirola</Cell><Cell>Jakub Mirola</Cell></Row>
<Row><Cell>cfnm_jackdaniels</Cell><Cell>Jason Herbert</Cell><Cell>Jason Herbert</Cell></Row>
<Row><Cell>cfnm_james4life</Cell><Cell>James4life</Cell><Cell>James4life</Cell></Row>
<Row><Cell>cfnm_jasonbroadley</Cell><Cell>Jaeger Zedwimer</Cell><Cell>Jaeger Zedwimer</Cell></Row>
<Row><Cell>cfnm_jb3275</Cell><Cell>Jb3275</Cell><Cell>Jb3276</Cell></Row>
<Row><Cell>cfnm_jeebuscripes</Cell><Cell>Ser Hugo James edberg</Cell><Cell>Ser Hugo James edberg</Cell></Row>
<Row><Cell>cfnm_jenks</Cell><Cell>Simon Jenkins</Cell><Cell>Simon Jenkins</Cell></Row>
<Row><Cell>cfnm_jezza</Cell><Cell>Edward of Caernarfon</Cell><Cell>Edward of Caernarfon</Cell></Row>
<Row><Cell>cfnm_jiri_zeman</Cell><Cell>Jiří Zeman</Cell><Cell>Jiří Zeman</Cell></Row>
<Row><Cell>cfnm_jjwashington77</Cell><Cell>James Washington</Cell><Cell>James Washington</Cell></Row>
<Row><Cell>cfnm_joebold</Cell><Cell>Gile Ethaine</Cell><Cell>Gile Ethaine</Cell></Row>
<Row><Cell>cfnm_joedycz</Cell><Cell>Jiří Joe Dykast</Cell><Cell>Jiří Joe Dykast</Cell></Row>
<Row><Cell>cfnm_johnnydement</Cell><Cell>Josep M Giribet</Cell><Cell>Josep M Giribet</Cell></Row>
<Row><Cell>cfnm_jokermidnight</Cell><Cell>Geoffrey Hise</Cell><Cell>Geoffrey Hise</Cell></Row>
<Row><Cell>cfnm_jomr3</Cell><Cell>Johan Martens</Cell><Cell>Johan Martens</Cell></Row>
<Row><Cell>cfnm_joquh</Cell><Cell>Christian Friedrich</Cell><Cell>Christian Friedrich</Cell></Row>
<Row><Cell>cfnm_jpiedmont</Cell><Cell>Jonathan Piedmont</Cell><Cell>Jonathan Piedmont</Cell></Row>
<Row><Cell>cfnm_jro107027gmailcom</Cell><Cell>JONN O'LENA</Cell><Cell>JONN O'LENA</Cell></Row>
<Row><Cell>cfnm_jtrtik</Cell><Cell>Lenka Trtíková</Cell><Cell>Lenka Trtíková</Cell></Row>
<Row><Cell>cfnm_julenlete</Cell><Cell>Julen Lete</Cell><Cell>Julen Lete</Cell></Row>
<Row><Cell>cfnm_kachelschmierer</Cell><Cell>Michael Kerscher</Cell><Cell>Michael Kerscher</Cell></Row>
<Row><Cell>cfnm_kajapa</Cell><Cell>Kajapa</Cell><Cell>Kajapa</Cell></Row>
<Row><Cell>cfnm_kan</Cell><Cell>Kan</Cell><Cell>Kan</Cell></Row>
<Row><Cell>cfnm_kasiny</Cell><Cell>Lukáš Glončák</Cell><Cell>Lukáš Glončák</Cell></Row>
<Row><Cell>cfnm_kawala</Cell><Cell>Eric Scholten</Cell><Cell>Eric Scholten</Cell></Row>
<Row><Cell>cfnm_kdeary</Cell><Cell>Kenneth Deary</Cell><Cell>Kenneth Deary</Cell></Row>
<Row><Cell>cfnm_keemosabi</Cell><Cell>Chris Knapp</Cell><Cell>Chris Knapp</Cell></Row>
<Row><Cell>cfnm_kenji_iwasaki</Cell><Cell>Kenji Iwasaki</Cell><Cell>Kenji Iwasaki</Cell></Row>
<Row><Cell>cfnm_kevyin</Cell><Cell>K Ying</Cell><Cell>K Ying</Cell></Row>
<Row><Cell>cfnm_khaziemer</Cell><Cell>Khaziemer</Cell><Cell>Khaziemer</Cell></Row>
<Row><Cell>cfnm_killashard</Cell><Cell>Gregory Pavelka</Cell><Cell>Gregory Pavelka</Cell></Row>
<Row><Cell>cfnm_king_domenico</Cell><Cell>Dominic Opipari</Cell><Cell>Dominic Opipari</Cell></Row>
<Row><Cell>cfnm_kinglukas</Cell><Cell>King Lukas</Cell><Cell>King Lukas</Cell></Row>
<Row><Cell>cfnm_kjeldor</Cell><Cell>David Hubený</Cell><Cell>David Hubený</Cell></Row>
<Row><Cell>cfnm_kjurer</Cell><Cell>Michael Kriz</Cell><Cell>Michael Kriz</Cell></Row>
<Row><Cell>cfnm_klingelnberg</Cell><Cell>Cristian Martin Lopez</Cell><Cell>Cristian Martin Lopez</Cell></Row>
<Row><Cell>cfnm_knighterrant</Cell><Cell>Miloš D.</Cell><Cell>Miloš D.</Cell></Row>
<Row><Cell>cfnm_kuma</Cell><Cell>Václav Míšek</Cell><Cell>Václav Míšek</Cell></Row>
<Row><Cell>cfnm_leaf16nut</Cell><Cell>justin byers</Cell><Cell>justin byers</Cell></Row>
<Row><Cell>cfnm_leonidasrjm</Cell><Cell>Rodrigo</Cell><Cell>Rodrigo</Cell></Row>
<Row><Cell>cfnm_leonpumpoi</Cell><Cell>Leonid Samoylovskiy</Cell><Cell>Leonid Samoylovskiy</Cell></Row>
<Row><Cell>cfnm_lipsch90</Cell><Cell>Michael Betschart</Cell><Cell>Michael Betschart</Cell></Row>
<Row><Cell>cfnm_lithon</Cell><Cell>Hazza Alkaabi</Cell><Cell>Hazza Alkaabi</Cell></Row>
<Row><Cell>cfnm_liyet</Cell><Cell>Y. K. Lee</Cell><Cell>Y. K. Lee</Cell></Row>
<Row><Cell>cfnm_lord_rundle</Cell><Cell>Right Honorable Lord Mayor Timothy C. Rundle</Cell><Cell>Right Honorable Lord Mayor Timothy C. Rundle</Cell></Row>
<Row><Cell>cfnm_lordcama</Cell><Cell>Florian</Cell><Cell>Florian</Cell></Row>
<Row><Cell>cfnm_lordpoision502</Cell><Cell>Christopher M. Campbell</Cell><Cell>Christopher M. Campbell</Cell></Row>
<Row><Cell>cfnm_lordy</Cell><Cell>Luca "Lordy" D'Addezio</Cell><Cell>Luca "Lordy" D'Addezio</Cell></Row>
<Row><Cell>cfnm_lucar85</Cell><Cell>Luca Rezzonico</Cell><Cell>Luca Rezzonico</Cell></Row>
<Row><Cell>cfnm_luib</Cell><Cell>Luib</Cell><Cell>Luib</Cell></Row>
<Row><Cell>cfnm_luis</Cell><Cell>Luis Soto Cros</Cell><Cell>Luis Soto Cros</Cell></Row>
<Row><Cell>cfnm_magicman300</Cell><Cell>Magicman300</Cell><Cell>Magicman301</Cell></Row>
<Row><Cell>cfnm_mahkcloud</Cell><Cell>MahkCloud</Cell><Cell>MahkCloud</Cell></Row>
<Row><Cell>cfnm_mak</Cell><Cell>Stéphane Welferinger</Cell><Cell>Stéphane Welferinger</Cell></Row>
<Row><Cell>cfnm_makar</Cell><Cell>Luboš Makarský</Cell><Cell>Luboš Makarský</Cell></Row>
<Row><Cell>cfnm_makoto</Cell><Cell>Christoph Konietzko</Cell><Cell>Christoph Konietzko</Cell></Row>
<Row><Cell>cfnm_maldunefarth</Cell><Cell>Maldanefarth</Cell><Cell>Maldanefarth</Cell></Row>
<Row><Cell>cfnm_manlor</Cell><Cell>Mika Mäkelä</Cell><Cell>Mika Mäkelä</Cell></Row>
<Row><Cell>cfnm_mario_santi</Cell><Cell>Mario A. Santi</Cell><Cell>Mario A. Santi</Cell></Row>
<Row><Cell>cfnm_martin8532</Cell><Cell>Martin Hartmann</Cell><Cell>Martin Hartmann</Cell></Row>
<Row><Cell>cfnm_math</Cell><Cell>math</Cell><Cell>math</Cell></Row>
<Row><Cell>cfnm_mattyb88</Cell><Cell>Matty Burney</Cell><Cell>Matty Burney</Cell></Row>
<Row><Cell>cfnm_maxgwenesef</Cell><Cell>Max Gwenesef</Cell><Cell>Max Gwenesef</Cell></Row>
<Row><Cell>cfnm_maykxor</Cell><Cell>Micah 'Maykxor' Smyth</Cell><Cell>Micah 'Maykxor' Smyth</Cell></Row>
<Row><Cell>cfnm_mccoshenc</Cell><Cell>Connor</Cell><Cell>Connor</Cell></Row>
<Row><Cell>cfnm_melkir</Cell><Cell>Robert Vögele</Cell><Cell>Robert Vögele</Cell></Row>
<Row><Cell>cfnm_metaldane</Cell><Cell>Metaldane</Cell><Cell>Metaldane</Cell></Row>
<Row><Cell>cfnm_metzgi</Cell><Cell>Martin Vorisek</Cell><Cell>Martin Vorisek</Cell></Row>
<Row><Cell>cfnm_michalproks</Cell><Cell>Michal Prokš</Cell><Cell>Michal Prokš</Cell></Row>
<Row><Cell>cfnm_michformer</Cell><Cell>Michformer</Cell><Cell>Michformer</Cell></Row>
<Row><Cell>cfnm_mildacmelak</Cell><Cell>Milan Čihák</Cell><Cell>Milan Čihák</Cell></Row>
<Row><Cell>cfnm_milkisgood1</Cell><Cell>Mikael Angil Cruz</Cell><Cell>Mikael Angil Cruz</Cell></Row>
<Row><Cell>cfnm_minko</Cell><Cell>Milan Kramár</Cell><Cell>Milan Kramár</Cell></Row>
<Row><Cell>cfnm_mitch74aus</Cell><Cell>Scott Mitchell</Cell><Cell>Scott Mitchell</Cell></Row>
<Row><Cell>cfnm_mivkiz</Cell><Cell>Kirill Evgenevich Grishnov</Cell><Cell>Kirill Evgenevich Grishnov</Cell></Row>
<Row><Cell>cfnm_modernatomic</Cell><Cell>Karel Buschmann</Cell><Cell>Karel Buschmann</Cell></Row>
<Row><Cell>cfnm_mogon</Cell><Cell>Mogon</Cell><Cell>Mogon</Cell></Row>
<Row><Cell>cfnm_molik</Cell><Cell>Petr Molík</Cell><Cell>Petr Molík</Cell></Row>
<Row><Cell>cfnm_morkham</Cell><Cell>Peder Myhr</Cell><Cell>Peder Myhr</Cell></Row>
<Row><Cell>cfnm_mortraven</Cell><Cell>Nicholas Taylor</Cell><Cell>Nicholas Taylor</Cell></Row>
<Row><Cell>cfnm_mrchr15topher</Cell><Cell>Christopher Mills</Cell><Cell>Christopher Mills</Cell></Row>
<Row><Cell>cfnm_mtzler</Cell><Cell>Michael Hopfenmüller</Cell><Cell>Michael Hopfenmüller</Cell></Row>
<Row><Cell>cfnm_n1ghtfly</Cell><Cell>JAKUB JIRUŠ</Cell><Cell>JAKUB JIRUŠ</Cell></Row>
<Row><Cell>cfnm_narflung</Cell><Cell>Narflung</Cell><Cell>Narflung</Cell></Row>
<Row><Cell>cfnm_narmondur</Cell><Cell>Miika Juhani Isoviita</Cell><Cell>Miika Juhani Isoviita</Cell></Row>
<Row><Cell>cfnm_narneda</Cell><Cell>Narneda</Cell><Cell>Narneda</Cell></Row>
<Row><Cell>cfnm_nathankenwabikise</Cell><Cell>Nathan Isak Kenwabikise</Cell><Cell>Nathan Isak Kenwabikise</Cell></Row>
<Row><Cell>cfnm_nekator</Cell><Cell>Rudolfir</Cell><Cell>Rudolfir</Cell></Row>
<Row><Cell>cfnm_nervzz</Cell><Cell>Julien Jordan</Cell><Cell>Julien Jordan</Cell></Row>
<Row><Cell>cfnm_nick2508</Cell><Cell>André Sens</Cell><Cell>André Sens</Cell></Row>
<Row><Cell>cfnm_nicolas</Cell><Cell>Nicolas Lukaschek</Cell><Cell>Nicolas Lukaschek</Cell></Row>
<Row><Cell>cfnm_nicotina</Cell><Cell>Aquiles Monaco Filho</Cell><Cell>Aquiles Monaco Filho</Cell></Row>
<Row><Cell>cfnm_nobry</Cell><Cell>Phan Nobry Ouk</Cell><Cell>Phan Nobry Ouk</Cell></Row>
<Row><Cell>cfnm_nordee</Cell><Cell>D. Nord</Cell><Cell>D. Nord</Cell></Row>
<Row><Cell>cfnm_northernaxe</Cell><Cell>Samuel-Richard Desaulniers</Cell><Cell>Samuel-Richard Desaulniers</Cell></Row>
<Row><Cell>cfnm_obergurukain</Cell><Cell>Andreas Schollenberger</Cell><Cell>Andreas Schollenberger</Cell></Row>
<Row><Cell>cfnm_ohioman101</Cell><Cell>Ryan Mannion</Cell><Cell>Ryan Mannion</Cell></Row>
<Row><Cell>cfnm_olavvi</Cell><Cell>Olav Vaage</Cell><Cell>Olav Vaage</Cell></Row>
<Row><Cell>cfnm_ondrej42</Cell><Cell>Ondřej Sim</Cell><Cell>Ondřej Sim</Cell></Row>
<Row><Cell>cfnm_oppressor</Cell><Cell>Patrick S Railing</Cell><Cell>Patrick S Railing</Cell></Row>
<Row><Cell>cfnm_osskozzot</Cell><Cell>Osskozzot</Cell><Cell>Osskozzot</Cell></Row>
<Row><Cell>cfnm_oszy</Cell><Cell>Oswald</Cell><Cell>Oswald</Cell></Row>
<Row><Cell>cfnm_outcast</Cell><Cell>stephen lister</Cell><Cell>stephen lister</Cell></Row>
<Row><Cell>cfnm_parry</Cell><Cell>Peter Thorsten Onnasch</Cell><Cell>Peter Thorsten Onnasch</Cell></Row>
<Row><Cell>cfnm_patches</Cell><Cell>Patches O´houlahan</Cell><Cell>Patches O´houlahan</Cell></Row>
<Row><Cell>cfnm_pedro</Cell><Cell>PEDRO IVO MARIANO</Cell><Cell>PEDRO IVO MARIANO</Cell></Row>
<Row><Cell>cfnm_peregrinus</Cell><Cell>Kelly Josef Kilgore</Cell><Cell>Kelly Josef Kilgore</Cell></Row>
<Row><Cell>cfnm_petr_novak</Cell><Cell>Petr Novák</Cell><Cell>Petr Novák</Cell></Row>
<Row><Cell>cfnm_phaidon</Cell><Cell>Pantelis Pasvantis</Cell><Cell>Pantelis Pasvantis</Cell></Row>
<Row><Cell>cfnm_pharoah4187</Cell><Cell>Aaron Richmond</Cell><Cell>Aaron Richmond</Cell></Row>
<Row><Cell>cfnm_phil1976</Cell><Cell>Phil1976</Cell><Cell>Phil1977</Cell></Row>
<Row><Cell>cfnm_phydra</Cell><Cell>Bonnie L Nadri</Cell><Cell>Bonnie L Nadri</Cell></Row>
<Row><Cell>cfnm_pickpocket31</Cell><Cell>Glenn Italiano</Cell><Cell>Glenn Italiano</Cell></Row>
<Row><Cell>cfnm_pkirby1966</Cell><Cell>Phil "Madbrit" Kirby</Cell><Cell>Phil "Madbrit" Kirby</Cell></Row>
<Row><Cell>cfnm_poripo</Cell><Cell>Sasagawa Ray</Cell><Cell>Sasagawa Ray</Cell></Row>
<Row><Cell>cfnm_porphyrogennetos</Cell><Cell>Kevin Wallace</Cell><Cell>Kevin Wallace</Cell></Row>
<Row><Cell>cfnm_produno</Cell><Cell>Marcus Crane</Cell><Cell>Marcus Crane</Cell></Row>
<Row><Cell>cfnm_psyco363</Cell><Cell>Michel Hauptlin</Cell><Cell>Michel Hauptlin</Cell></Row>
<Row><Cell>cfnm_psychozoa</Cell><Cell>Psychozoa</Cell><Cell>Psychozoa</Cell></Row>
<Row><Cell>cfnm_ptbbcc</Cell><Cell>Bob Schröder</Cell><Cell>Bob Schröder</Cell></Row>
<Row><Cell>cfnm_qwentis</Cell><Cell>Abdulaziz Al Matrooshi</Cell><Cell>Abdulaziz Al Matrooshi</Cell></Row>
<Row><Cell>cfnm_r0b0b0b0r</Cell><Cell>Róbert Winkler</Cell><Cell>Róbert Winkler</Cell></Row>
<Row><Cell>cfnm_ra6475</Cell><Cell>Václav Rajnoha</Cell><Cell>Václav Rajnoha</Cell></Row>
<Row><Cell>cfnm_raculot</Cell><Cell>William Lassen</Cell><Cell>William Lassen</Cell></Row>
<Row><Cell>cfnm_radekkaspar</Cell><Cell>Radek Kašpar</Cell><Cell>Radek Kašpar</Cell></Row>
<Row><Cell>cfnm_ragnol</Cell><Cell>Sarah Canniffe</Cell><Cell>Sarah Canniffe</Cell></Row>
<Row><Cell>cfnm_ralin821</Cell><Cell>Ralin821</Cell><Cell>Ralin822</Cell></Row>
<Row><Cell>cfnm_ranadiel</Cell><Cell>Matthew Davison</Cell><Cell>Matthew Davison</Cell></Row>
<Row><Cell>cfnm_random121</Cell><Cell>Random121</Cell><Cell>Random122</Cell></Row>
<Row><Cell>cfnm_reaper</Cell><Cell>Dylan Lesley</Cell><Cell>Dylan Lesley</Cell></Row>
<Row><Cell>cfnm_revek</Cell><Cell>Roscoe Fay</Cell><Cell>Roscoe Fay</Cell></Row>
<Row><Cell>cfnm_revil821</Cell><Cell>revil</Cell><Cell>revil</Cell></Row>
<Row><Cell>cfnm_rgbvaz</Cell><Cell>Vsevolod Zaikov</Cell><Cell>Vsevolod Zaikov</Cell></Row>
<Row><Cell>cfnm_richard_of_fall</Cell><Cell>Richard_of_fall</Cell><Cell>Richard_of_fall</Cell></Row>
<Row><Cell>cfnm_rik</Cell><Cell>Beneš z Ladiměřic</Cell><Cell>Beneš z Ladiměřic</Cell></Row>
<Row><Cell>cfnm_roden_ruzgar</Cell><Cell>Timothy Montano</Cell><Cell>Timothy Montano</Cell></Row>
<Row><Cell>cfnm_royalvoice</Cell><Cell>Devin humphrey</Cell><Cell>Devin humphrey</Cell></Row>
<Row><Cell>cfnm_ruprecht_iii</Cell><Cell>Michael Hedderich</Cell><Cell>Michael Hedderich</Cell></Row>
<Row><Cell>cfnm_sammoroth</Cell><Cell>Sam Paley</Cell><Cell>Sam Paley</Cell></Row>
<Row><Cell>cfnm_sashamhk</Cell><Cell>Sasha Mhk</Cell><Cell>Sasha Mhk</Cell></Row>
<Row><Cell>cfnm_sblomkamp</Cell><Cell>Lawrence Conrad Blomkamp</Cell><Cell>Lawrence Conrad Blomkamp</Cell></Row>
<Row><Cell>cfnm_sbuck</Cell><Cell>Shawn</Cell><Cell>Shawn</Cell></Row>
<Row><Cell>cfnm_scarfy</Cell><Cell>Jan Kovats de ujthorda</Cell><Cell>Jan Kovats de ujthorda</Cell></Row>
<Row><Cell>cfnm_scotty</Cell><Cell>Roman Plch</Cell><Cell>Roman Plch</Cell></Row>
<Row><Cell>cfnm_sdfprowler</Cell><Cell>Sdf Prowler</Cell><Cell>Sdf Prowler</Cell></Row>
<Row><Cell>cfnm_sealawyer</Cell><Cell>Dohnal Clark Atkinson</Cell><Cell>Dohnal Clark Atkinson</Cell></Row>
<Row><Cell>cfnm_seandave</Cell><Cell>Sean</Cell><Cell>Sean</Cell></Row>
<Row><Cell>cfnm_secretlars</Cell><Cell>Lars-Wictor Dean Abrahamsson</Cell><Cell>Lars-Wictor Dean Abrahamsson</Cell></Row>
<Row><Cell>cfnm_serenogas</Cell><Cell>Tobias zu Huchilheym</Cell><Cell>Tobias zu Huchilheym</Cell></Row>
<Row><Cell>cfnm_serval</Cell><Cell>Gomir</Cell><Cell>Gomir</Cell></Row>
<Row><Cell>cfnm_shamirr</Cell><Cell>Shamirr</Cell><Cell>Shamirr</Cell></Row>
<Row><Cell>cfnm_shandrilessa</Cell><Cell>Christian Opilio</Cell><Cell>Christian Opilio</Cell></Row>
<Row><Cell>cfnm_sharp</Cell><Cell>Sharp</Cell><Cell>Sharp</Cell></Row>
<Row><Cell>cfnm_shealladh</Cell><Cell>Shealladh</Cell><Cell>Shealladh</Cell></Row>
<Row><Cell>cfnm_sherpa76</Cell><Cell>Gyuman Yoon</Cell><Cell>Gyuman Yoon</Cell></Row>
<Row><Cell>cfnm_shigawire</Cell><Cell>John Bernhard Horn</Cell><Cell>John Bernhard Horn</Cell></Row>
<Row><Cell>cfnm_siannah</Cell><Cell>Siannah</Cell><Cell>Siannah</Cell></Row>
<Row><Cell>cfnm_silentone2k</Cell><Cell>Ryan</Cell><Cell>Ryan</Cell></Row>
<Row><Cell>cfnm_simenb91</Cell><Cell>Simen Bekkhus</Cell><Cell>Simen Bekkhus</Cell></Row>
<Row><Cell>cfnm_sirax</Cell><Cell>Tobias Zaugg</Cell><Cell>Tobias Zaugg</Cell></Row>
<Row><Cell>cfnm_skuphundaku</Cell><Cell>Skuphundaku</Cell><Cell>Skuphundaku</Cell></Row>
<Row><Cell>cfnm_smoil</Cell><Cell>Tino Aigner</Cell><Cell>Tino Aigner</Cell></Row>
<Row><Cell>cfnm_solearis</Cell><Cell>Tomáš Berecz</Cell><Cell>Tomáš Berecz</Cell></Row>
<Row><Cell>cfnm_sp1nzok</Cell><Cell>Ville Hahtonen</Cell><Cell>Ville Hahtonen</Cell></Row>
<Row><Cell>cfnm_spagr</Cell><Cell>Spagr</Cell><Cell>Spagr</Cell></Row>
<Row><Cell>cfnm_spoonkdk</Cell><Cell>Daniel Busk</Cell><Cell>Daniel Busk</Cell></Row>
<Row><Cell>cfnm_stefan_bosch</Cell><Cell>Stefan Bosch</Cell><Cell>Stefan Bosch</Cell></Row>
<Row><Cell>cfnm_stein</Cell><Cell>Stein</Cell><Cell>Stein</Cell></Row>
<Row><Cell>cfnm_steskipper</Cell><Cell>Stefano </Cell><Cell>Stefano </Cell></Row>
<Row><Cell>cfnm_stevee</Cell><Cell>Steven Evanson</Cell><Cell>Steven Evanson</Cell></Row>
<Row><Cell>cfnm_stilgars</Cell><Cell>Julien A. Feraud</Cell><Cell>Julien A. Feraud</Cell></Row>
<Row><Cell>cfnm_stridsvarg</Cell><Cell>Njål Moland</Cell><Cell>Njål Moland</Cell></Row>
<Row><Cell>cfnm_suldanessala</Cell><Cell>Thomas the bearded one</Cell><Cell>Thomas the bearded one</Cell></Row>
<Row><Cell>cfnm_swordmaster</Cell><Cell>Brian Schorr</Cell><Cell>Brian Schorr</Cell></Row>
<Row><Cell>cfnm_tajo77</Cell><Cell>Sebastian Scheel</Cell><Cell>Sebastian Scheel</Cell></Row>
<Row><Cell>cfnm_tcberry</Cell><Cell>Timothy</Cell><Cell>Timothy</Cell></Row>
<Row><Cell>cfnm_teutdelamorte</Cell><Cell>Teut de Lepell</Cell><Cell>Teut de Lepell</Cell></Row>
<Row><Cell>cfnm_themalfeis</Cell><Cell>Jaromir</Cell><Cell>Jaromir</Cell></Row>
<Row><Cell>cfnm_thorir</Cell><Cell>Michal Zoldak</Cell><Cell>Michal Zoldak</Cell></Row>
<Row><Cell>cfnm_timtaalik</Cell><Cell>Timothy TWK</Cell><Cell>Timothy TWK</Cell></Row>
<Row><Cell>cfnm_tj4590</Cell><Cell>Taylor Wheatcroft</Cell><Cell>Taylor Wheatcroft</Cell></Row>
<Row><Cell>cfnm_toad</Cell><Cell>Memento Mori, F.H</Cell><Cell>Memento Mori, F.H</Cell></Row>
<Row><Cell>cfnm_tob</Cell><Cell>Zakeran</Cell><Cell>Zakeran</Cell></Row>
<Row><Cell>cfnm_tom_forro</Cell><Cell>Tom Forro</Cell><Cell>Tom Forro</Cell></Row>
<Row><Cell>cfnm_tonycoolmen</Cell><Cell>Michael Feuerbach</Cell><Cell>Michael Feuerbach</Cell></Row>
<Row><Cell>cfnm_topperfalkon</Cell><Cell>Harley Faggetter</Cell><Cell>Harley Faggetter</Cell></Row>
<Row><Cell>cfnm_trickster_loki</Cell><Cell>Daniel Waters</Cell><Cell>Daniel Waters</Cell></Row>
<Row><Cell>cfnm_tumapetr</Cell><Cell>Tůma Petr</Cell><Cell>Tůma Petr</Cell></Row>
<Row><Cell>cfnm_typisch</Cell><Cell>} Mario Haink }</Cell><Cell>} Mario Haink }</Cell></Row>
<Row><Cell>cfnm_ucan</Cell><Cell>Jari Kaasalainen</Cell><Cell>Jari Kaasalainen</Cell></Row>
<Row><Cell>cfnm_ufenloh</Cell><Cell>Ufenloh</Cell><Cell>Ufenloh</Cell></Row>
<Row><Cell>cfnm_ugubu</Cell><Cell>Ugubu Konno</Cell><Cell>Ugubu Konno</Cell></Row>
<Row><Cell>cfnm_ulvgrim</Cell><Cell>Reiner Gabold</Cell><Cell>Reiner Gabold</Cell></Row>
<Row><Cell>cfnm_uncontested</Cell><Cell>Branden Lynch</Cell><Cell>Branden Lynch</Cell></Row>
<Row><Cell>cfnm_unwissend</Cell><Cell>Björn</Cell><Cell>Björn</Cell></Row>
<Row><Cell>cfnm_urban</Cell><Cell>Louis Britton</Cell><Cell>Louis Britton</Cell></Row>
<Row><Cell>cfnm_ureakim</Cell><Cell>Ureakim</Cell><Cell>Ureakim</Cell></Row>
<Row><Cell>cfnm_utsuro</Cell><Cell>Matt McRae</Cell><Cell>Matt McRae</Cell></Row>
<Row><Cell>cfnm_uweschneider</Cell><Cell>Uwe Schneider</Cell><Cell>Uwe Schneider</Cell></Row>
<Row><Cell>cfnm_valiantloki</Cell><Cell>Stephan M Travers</Cell><Cell>Stephan M Travers</Cell></Row>
<Row><Cell>cfnm_valinblade</Cell><Cell>S.Shepherd</Cell><Cell>S.Shepherd</Cell></Row>
<Row><Cell>cfnm_vanefox</Cell><Cell>VaneFox</Cell><Cell>VaneFox</Cell></Row>
<Row><Cell>cfnm_vargasgray</Cell><Cell>Robin Wemmenlöv</Cell><Cell>Robin Wemmenlöv</Cell></Row>
<Row><Cell>cfnm_versusevil</Cell><Cell>Versus Evil</Cell><Cell>Versus Evil</Cell></Row>
<Row><Cell>cfnm_viking12</Cell><Cell>William Robert Vking Potts</Cell><Cell>William Robert Vking Potts</Cell></Row>
<Row><Cell>cfnm_vilem</Cell><Cell>Vilém Kledrowetz</Cell><Cell>Vilém Kledrowetz</Cell></Row>
<Row><Cell>cfnm_virus</Cell><Cell>ViRus</Cell><Cell>ViRus</Cell></Row>
<Row><Cell>cfnm_vistix</Cell><Cell>Gašper Bogovič</Cell><Cell>Gašper Bogovič</Cell></Row>
<Row><Cell>cfnm_vonuberk</Cell><Cell>kristjan smith</Cell><Cell>kristjan smith</Cell></Row>
<Row><Cell>cfnm_waldkauz</Cell><Cell>Gerhard Swihla</Cell><Cell>Gerhard Swihla</Cell></Row>
<Row><Cell>cfnm_wardenking</Cell><Cell>Daniel Buerengen</Cell><Cell>Daniel Buerengen</Cell></Row>
<Row><Cell>cfnm_warhols</Cell><Cell>Warhols</Cell><Cell>Warhols</Cell></Row>
<Row><Cell>cfnm_wenedros</Cell><Cell>Martin Steklý z Loun</Cell><Cell>Martin Steklý z Loun</Cell></Row>
<Row><Cell>cfnm_wikc</Cell><Cell>Toni</Cell><Cell>Toni</Cell></Row>
<Row><Cell>cfnm_wildstalliondc</Cell><Cell>Dakota Scott Cisco</Cell><Cell>Dakota Scott Cisco</Cell></Row>
<Row><Cell>cfnm_wlorca</Cell><Cell>Walter Lorca</Cell><Cell>Walter Lorca</Cell></Row>
<Row><Cell>cfnm_wolarion</Cell><Cell>Antti Ruokonen</Cell><Cell>Antti Ruokonen</Cell></Row>
<Row><Cell>cfnm_wolfgang1st</Cell><Cell>Wolfgang Schrenk</Cell><Cell>Wolfgang Schrenk</Cell></Row>
<Row><Cell>cfnm_woody</Cell><Cell>Verunka</Cell><Cell>Verunka</Cell></Row>
<Row><Cell>cfnm_woutertje</Cell><Cell>Wouter</Cell><Cell>Wouter</Cell></Row>
<Row><Cell>cfnm_wrothamon</Cell><Cell>WrothAmon</Cell><Cell>WrothAmon</Cell></Row>
<Row><Cell>cfnm_xaquz</Cell><Cell>Xaquz</Cell><Cell>Xaquz</Cell></Row>
<Row><Cell>cfnm_xing</Cell><Cell>Xing</Cell><Cell>Xing</Cell></Row>
<Row><Cell>cfnm_xmutant</Cell><Cell>Martin Lupač</Cell><Cell>Martin Lupač</Cell></Row>
<Row><Cell>cfnm_yasu246</Cell><Cell>Yatchi</Cell><Cell>Yatchi</Cell></Row>
<Row><Cell>cfnm_yggrgmxnet</Cell><Cell>Henning Klaßen</Cell><Cell>Henning Klaßen</Cell></Row>
<Row><Cell>cfnm_yuusouamazing</Cell><Cell>Yuusouamazing</Cell><Cell>Yuusouamazing</Cell></Row>
<Row><Cell>cfnm_z3p</Cell><Cell>Zepar</Cell><Cell>Zepar</Cell></Row>
<Row><Cell>cfnm_zala_</Cell><Cell>Zala</Cell><Cell>Zala</Cell></Row>
<Row><Cell>cfnm_zarlor</Cell><Cell>Leonard Zimmermann</Cell><Cell>Leonard Zimmermann</Cell></Row>
<Row><Cell>cfnm_zeekay980</Cell><Cell>Zack Kelly</Cell><Cell>Zack Kelly</Cell></Row>
<Row><Cell>cfnm_zeretal</Cell><Cell>Alex Brown</Cell><Cell>Alex Brown</Cell></Row>
<Row><Cell>cfnm_zero32000</Cell><Cell>Manuel Aban Mangrobang IV</Cell><Cell>Manuel Aban Mangrobang IV</Cell></Row>
<Row><Cell>cfnm_zold54</Cell><Cell>Tomas Zoldak</Cell><Cell>Tomas Zoldak</Cell></Row>
<Row><Cell>close_door</Cell><Cell>Close door</Cell><Cell>Zamknij drzwi</Cell></Row>
<Row><Cell>dlg_alch_autocook</Cell><Cell>Start autobrewing? Current progress will be lost.</Cell><Cell>Zacznij autogotowanie. Obecny postęp w grze zostanie usunięty.</Cell></Row>
<Row><Cell>dlg_alch_autocook_info</Cell><Cell>If you start automatic brewing, the ingredients you already used will be lost.</Cell><Cell>Jeśli zaczniesz autogotowanie, wszystkie dotąd użyte składniki przepadną.</Cell></Row>
<Row><Cell>dlg_alch_autocook_not_cooked</Cell><Cell>You can't autobrew this potion until you've first brewed it by hand.</Cell><Cell>Nie możesz uwarzyć tego eliksiru za pomocą autogotowania, dopóki najpierw nie przygotujesz go ręcznie.</Cell></Row>
<Row><Cell>dlg_alch_autocook_not_enabled</Cell><Cell>You need a higher level to unlock autobrew functionality.</Cell><Cell>Potrzebujesz mieć większe doświadczenie w alchemii, aby otworzyć opcję autogotowania.</Cell></Row>
<Row><Cell>dlg_alch_cannot_autocook</Cell><Cell>You don't know the whole recipe.</Cell><Cell>Nie znasz całego przepisu.</Cell></Row>
<Row><Cell>dlg_alch_end_cooking</Cell><Cell>Finish brewing?</Cell><Cell>Dokończ warzyć i wlej eliksir do fiolki.</Cell></Row>
<Row><Cell>dlg_alch_end_cooking_info</Cell><Cell>This will complete the potion</Cell><Cell>Tym zakończysz sporządzanie eliksiru.</Cell></Row>
<Row><Cell>dlg_alch_exit</Cell><Cell>Are you sure you want to leave the bench? Current progress will be lost.</Cell><Cell>Jesteś pewien, że chcesz odejść od stołu? Wszystkie niezapisane postępy w grze zostaną usunięte.</Cell></Row>
<Row><Cell>dlg_alch_exit_info</Cell><Cell>If you leave the bench now, all used ingredients will be lost!</Cell><Cell>Jeśli teraz odejdziesz od stołu, wszystkie użyte składniki przepadną.</Cell></Row>
<Row><Cell>dlg_alch_many_ingredients</Cell><Cell>No more ingredients can be added.</Cell><Cell>Nie można dodać dalszych składników.</Cell></Row>
<Row><Cell>dlg_alch_not_all_ingredients</Cell><Cell>You don't have all the ingredients for this recipe.</Cell><Cell>Nie masz wszystkich składników do wykonania tego przepisu.</Cell></Row>
<Row><Cell>dlg_alch_potion_created</Cell><Cell>You've brewed </Cell><Cell>Uwarzyłeś:</Cell></Row>
<Row><Cell>dlg_alch_prepare</Cell><Cell>Prepare the bench for this recipe? The ingredients you already used will be lost.</Cell><Cell>Przygotuj stół do wykonania tego przepisu. Wszystkie dotąd użyte składniki przepadną.</Cell></Row>
<Row><Cell>dlg_alch_prepare_info</Cell><Cell>If you start brewing a new recipe, the ingredients already used will be lost.</Cell><Cell>Jeśli zaczniesz nowy przepis, wszystkie dotąd użyte składniki przepadną.</Cell></Row>
<Row><Cell>dlg_alch_recipe_already_unlocked</Cell><Cell>You already know this recipe.</Cell><Cell>Już znasz ten przepis.</Cell></Row>
<Row><Cell>dlg_alch_recipe_failed</Cell><Cell>Potion brewing has failed. All ingredients are lost.</Cell><Cell>Nie udało się uwarzyć eliksiru. Utracono wszystkie składniki.</Cell></Row>
<Row><Cell>dlg_alch_recipe_step_unlocked</Cell><Cell>You've discovered a new recipe step.</Cell><Cell>Odkryto nowy krok w przepisie.</Cell></Row>
<Row><Cell>dlg_alch_recipe_steps_unlocked</Cell><Cell>You've discovered new recipe steps.</Cell><Cell>Odkryto kroki, aby udzielać nowy przepis.</Cell></Row>
<Row><Cell>dlg_alch_recipe_unlocked</Cell><Cell>You've discovered a new recipe.</Cell><Cell>Odkryto nowy przepis.</Cell></Row>
<Row><Cell>dlg_alch_reset_unneccessary</Cell><Cell>Bench is already set up for brewing a new recipe.</Cell><Cell>Stół jest gotowy do przygotowania nowego przepisu.</Cell></Row>
<Row><Cell>dlg_alch_resettable</Cell><Cell>Reset the bench? Current progress will be lost.</Cell><Cell>Wyczyść stół. Obecny postęp zostanie usunięty.</Cell></Row>
<Row><Cell>dlg_alch_resettable_info</Cell><Cell>If you reset the bench now, all the ingredients you used will be lost.</Cell><Cell>Jeśli teraz wyczyścisz stół, wszystkie składniki przepadną.</Cell></Row>
<Row><Cell>dlg_cannotStartMinigame</Cell><Cell>Can't start</Cell><Cell>Nie można zacząć</Cell></Row>
<Row><Cell>dlg_confirmStealingItem</Cell><Cell>Are you sure you want to steal this item?</Cell><Cell>Jesteś pewien, że chcesz ukraść ten przedmiot?</Cell></Row>
<Row><Cell>dlg_hd_cannotStart</Cell><Cell>You don't have a spade!</Cell><Cell>Nie masz łopaty!</Cell></Row>
<Row><Cell>dlg_horse_cannotMount</Cell><Cell>You're too overloaded to mount up!</Cell><Cell>Jesteś zbyt przeciążony, by wsiąść na konia!</Cell></Row>
<Row><Cell>dlg_lp_cannotStart</Cell><Cell>You don't have a lockpick!</Cell><Cell>Nie masz wytrychu!</Cell></Row>
<Row><Cell>dlg_lp_difficult</Cell><Cell>This lock is very difficult for you. Are you going to try it anyway?</Cell><Cell>Ten zamek jest bardzo trudny do otwarcia. Czy spróbujesz i tak go otworzyć?</Cell></Row>
<Row><Cell>dlg_lp_difficult_info</Cell><Cell>This lock is too difficult.</Cell><Cell>Ten zamek jest za trudny do otworzenia. </Cell></Row>
<Row><Cell>dlg_no</Cell><Cell>No</Cell><Cell>Nie</Cell></Row>
<Row><Cell>dlg_ok</Cell><Cell>OK</Cell><Cell>Ok</Cell></Row>
<Row><Cell>dlg_yes</Cell><Cell>Yes</Cell><Cell>Tak</Cell></Row>
<Row><Cell>hud_low_ammo</Cell><Cell>LOW AMMO!</Cell><Cell>NISKI STAN AMUNICJI!</Cell></Row>
<Row><Cell>hud_mp_joined_game</Cell><Cell>joined the game</Cell><Cell>Przyłączył się do gry</Cell></Row>
<Row><Cell>hud_mp_killed</Cell><Cell>killed</Cell><Cell>Zabity</Cell></Row>
<Row><Cell>hud_mp_left_game</Cell><Cell>left the game</Cell><Cell>Opuścił grę</Cell></Row>
<Row><Cell>hud_mp_self_killed</Cell><Cell>killed himself</Cell><Cell>Zabił się</Cell></Row>
<Row><Cell>hud_out_of_ammo</Cell><Cell>OUT OF AMMO!</Cell><Cell>BRAK AMUNICJI!</Cell></Row>
<Row><Cell>log_dog_hunt_tired</Cell><Cell>Your dog is tired from hunting.</Cell><Cell>Twój pies jest zmęczony polowaniem.</Cell></Row>
<Row><Cell>log_game_load_failed</Cell><Cell>Game load failed</Cell><Cell>Wczytywanie gry nie powiodło się</Cell></Row>
<Row><Cell>log_game_loaded</Cell><Cell>Game loaded</Cell><Cell>Wczytaj grę</Cell></Row>
<Row><Cell>log_game_save_delete_failed</Cell><Cell>Game deletion failed</Cell><Cell>Usunięcie zapisanej gry nie powiodło się.</Cell></Row>
<Row><Cell>log_game_save_failed</Cell><Cell>Game save failed</Cell><Cell>Gry nie udało się zapisać</Cell></Row>
<Row><Cell>log_game_saved</Cell><Cell>Game saved</Cell><Cell>Gra została zapisana</Cell></Row>
<Row><Cell>log_horse_whistle_supressed</Cell><Cell>Your horse can't get here</Cell><Cell>Twój koń nie może się tu dostać.</Cell></Row>
<Row><Cell>log_no_quicksave</Cell><Cell>No quicksave found</Cell><Cell>Szybki zapis nie został znaleziony</Cell></Row>
<Row><Cell>open_door</Cell><Cell>Open door</Cell><Cell>Otwórz drzwi</Cell></Row>
<Row><Cell>q_millerDate_sitDownWithTereza</Cell><Cell>Sit with Theresa</Cell><Cell>Usiądź z Teresą</Cell></Row>
<Row><Cell>q_sickbastard_meat</Cell><Cell>You've found some stinking meat in this larder. Who does it belong to?</Cell><Cell>Znalazłeś jakąś śmierdzącą padlinę w tej spiżarni. Do kogo należy?</Cell></Row>
<Row><Cell>quest_completed</Cell><Cell>Quest completed:</Cell><Cell>Zadanie wykonane</Cell></Row>
<Row><Cell>quest_failed</Cell><Cell>Quest failed:</Cell><Cell>Nieudane zadanie:</Cell></Row>
<Row><Cell>quest_started</Cell><Cell>Quest started: </Cell><Cell>Rozpoczęto zadanie:</Cell></Row>
<Row><Cell>trigger_grave_Johanka</Cell><Cell>Johanka's grave</Cell><Cell>Grób Johanki.</Cell></Row>
<Row><Cell>trigger_grave_Matej</Cell><Cell>Matthias' grave</Cell><Cell>Grób Macieja.</Cell></Row>
<Row><Cell>trigger_modleni</Cell><Cell>Pray</Cell><Cell>Módl się</Cell></Row>
<Row><Cell>ui_back_prompt</Cell><Cell>(Back)</Cell><Cell>(Powrót)</Cell></Row>
<Row><Cell>ui_body_dead</Cell><Cell>(dead)</Cell><Cell>(nie żyje)</Cell></Row>
<Row><Cell>ui_body_unconscious</Cell><Cell>(unconscious)</Cell><Cell>(bez przytomności)</Cell></Row>
<Row><Cell>ui_close_stash</Cell><Cell>Close</Cell><Cell>Zamknij</Cell></Row>
<Row><Cell>ui_codex_new_entry</Cell><Cell>New Codex entry</Cell><Cell>Nowe hasło w Kodeksie.</Cell></Row>
<Row><Cell>ui_cook_item</Cell><Cell>Cook item</Cell><Cell>Ugotuj</Cell></Row>
<Row><Cell>ui_crime_confiscation_1</Cell><Cell>A stolen item has been confiscated from your inventory.</Cell><Cell>Ukradziony przedmiot z twojego inwentarza został skonfiskowany.</Cell></Row>
<Row><Cell>ui_crime_confiscation_10</Cell><Cell>Ten stolen items have been confiscated from your inventory.</Cell><Cell>Dziesięć skradzionych przedmiotów z twojego inwentarza zostało skonfiskowanych.</Cell></Row>
<Row><Cell>ui_crime_confiscation_11</Cell><Cell>Eleven stolen items have been confiscated from your inventory.</Cell><Cell>Jedenaście skradzionych przedmiotów z twojego inwentarza zostało skonfiskowanych.</Cell></Row>
<Row><Cell>ui_crime_confiscation_12</Cell><Cell>Twelve stolen items have been confiscated from your inventory.</Cell><Cell>Dwanaście skradzionych przedmiotów z twojego inwentarza zostało skonfiskowanych.</Cell></Row>
<Row><Cell>ui_crime_confiscation_13_plus</Cell><Cell>More than twelve stolen items have been confiscated from your inventory.</Cell><Cell>Więcej niż dwanaście skradzionych przedmiotów z twojego inwentarza zostało skonfiskowanych.</Cell></Row>
<Row><Cell>ui_crime_confiscation_2</Cell><Cell>Two stolen items have been confiscated from your inventory.</Cell><Cell>Dwa skradzione przedmioty z twojego inwentarza zostały skonfiskowane.</Cell></Row>
<Row><Cell>ui_crime_confiscation_3</Cell><Cell>Three stolen items have been confiscated from your inventory.</Cell><Cell>Trzy skradzione przedmioty z twojego inwentarza zostały skonfiskowane.</Cell></Row>
<Row><Cell>ui_crime_confiscation_4</Cell><Cell>Four stolen items have been confiscated from your inventory.</Cell><Cell>Cztery skradzione przedmioty z twojego inwentarza zostały skonfiskowane.</Cell></Row>
<Row><Cell>ui_crime_confiscation_5</Cell><Cell>Five stolen items have been confiscated from your inventory.</Cell><Cell>Pięć skradzionych przedmiotów z twojego inwentarza zostało skonfiskowanych.</Cell></Row>
<Row><Cell>ui_crime_confiscation_6</Cell><Cell>Six stolen items have been confiscated from your inventory.</Cell><Cell>Sześć skradzionych przedmiotów z twojego inwentarza zostało skonfiskowanych.</Cell></Row>
<Row><Cell>ui_crime_confiscation_7</Cell><Cell>Seven stolen items have been confiscated from your inventory.</Cell><Cell>Siedem skradzionych przedmiotów z twojego inwentarza zostało skonfiskowanych.</Cell></Row>
<Row><Cell>ui_crime_confiscation_8</Cell><Cell>Eight stolen items have been confiscated from your inventory.</Cell><Cell>Osiem skradzionych przedmiotów z twojego inwentarza zostało skonfiskowanych.</Cell></Row>
<Row><Cell>ui_crime_confiscation_9</Cell><Cell>Nine stolen items have been confiscated from your inventory.</Cell><Cell>Dziewięć skradzionych przedmiotów z twojego inwentarza zostało skonfiskowanych.</Cell></Row>
<Row><Cell>ui_crime_jail_placeholder</Cell><Cell>Luckily for you, there is no city with a jail in this technical alpha version. You're starving and exhausted instead! Your reputation across the land has also taken a serious hit.</Cell><Cell>Szczęśliwie dla ciebie, w tej technicznej wersji alpha nie ma żadnego miasta z więzieniem. Za to głodujesz i jesteś wyczerpany! Także twoja reputacja na całej ziemi została poważnie nadszarpnięta.</Cell></Row>
<Row><Cell>ui_default</Cell><Cell>Use</Cell><Cell>Użyj</Cell></Row>
<Row><Cell>ui_dialog_input_1</Cell><Cell>Haggling</Cell><Cell>Targuj się</Cell></Row>
<Row><Cell>ui_dialog_input_2</Cell><Cell>Bribery</Cell><Cell>Łapówka</Cell></Row>
<Row><Cell>ui_dialog_input_3</Cell><Cell>Bet</Cell><Cell>Załóż się</Cell></Row>
<Row><Cell>ui_dialoggroup0</Cell><Cell>Training</Cell><Cell>Trening</Cell></Row>
<Row><Cell>ui_dialoggroup1</Cell><Cell>Training combat</Cell><Cell>Trening walki</Cell></Row>
<Row><Cell>ui_dialoggroup8</Cell><Cell>Behaviour…</Cell><Cell>Zachowanie...</Cell></Row>
<Row><Cell>ui_dialoggroup9</Cell><Cell>Random Talk…</Cell><Cell>Przypadkowa rozmowa...</Cell></Row>
<Row><Cell>ui_dice_bust</Cell><Cell>Bust!</Cell><Cell>Skucha!</Cell></Row>
<Row><Cell>ui_dice_round</Cell><Cell>round</Cell><Cell>Tura</Cell></Row>
<Row><Cell>ui_dice_selected</Cell><Cell>selected</Cell><Cell>Wybrane</Cell></Row>
<Row><Cell>ui_dice_total</Cell><Cell>total</Cell><Cell>Suma</Cell></Row>
<Row><Cell>ui_dice_you_gave_up</Cell><Cell>You gave up!</Cell><Cell>Poddałeś się!</Cell></Row>
<Row><Cell>ui_dice_you_gave_up_female</Cell><Cell>You gave up!</Cell><Cell>Poddałaś się!</Cell></Row>
<Row><Cell>ui_dice_you_lost</Cell><Cell>You lost!</Cell><Cell>Przegrałeś!</Cell></Row>
<Row><Cell>ui_dice_you_lost_female</Cell><Cell>You lost!</Cell><Cell>Przegrałaś!</Cell></Row>
<Row><Cell>ui_dice_you_won</Cell><Cell>You won!</Cell><Cell>Wygrałeś!</Cell></Row>
<Row><Cell>ui_dice_you_won_female</Cell><Cell>You won!</Cell><Cell>Wygrałaś!</Cell></Row>
<Row><Cell>ui_dlg_cannot_overskip</Cell><Cell>You can't skip more hours now!</Cell><Cell>Nie możesz teraz pominąć więcej czasu!</Cell></Row>
<Row><Cell>ui_dog_attack</Cell><Cell>Sic!</Cell><Cell>Bierz!</Cell></Row>
<Row><Cell>ui_dog_fetch</Cell><Cell>Fetch!</Cell><Cell>Przynieś!</Cell></Row>
<Row><Cell>ui_dog_heel</Cell><Cell>Heel!</Cell><Cell>Do nogi!</Cell></Row>
<Row><Cell>ui_dog_hunt</Cell><Cell>Hunt!</Cell><Cell>Poluj!</Cell></Row>
<Row><Cell>ui_door_close</Cell><Cell>Close</Cell><Cell>Zamknij</Cell></Row>
<Row><Cell>ui_door_open</Cell><Cell>Open</Cell><Cell>Otwórz</Cell></Row>
<Row><Cell>ui_east_shortcut</Cell><Cell>E</Cell><Cell>E</Cell></Row>
<Row><Cell>ui_eat_kettle</Cell><Cell>Eat from pot</Cell><Cell>Jedz z garnka</Cell></Row>
<Row><Cell>ui_end_topic</Cell><Cell>(End dialog)</Cell><Cell>(Koniec rozmowy)</Cell></Row>
<Row><Cell>ui_epilogue_jost</Cell><Cell>Take the letter</Cell><Cell>Weź list.</Cell></Row>
<Row><Cell>ui_game_finished</Cell><Cell>Game finished</Cell><Cell>Gra została ukończona</Cell></Row>
<Row><Cell>ui_game_over</Cell><Cell>Game over</Cell><Cell>Koniec gry</Cell></Row>
<Row><Cell>ui_get</Cell><Cell>get</Cell><Cell>Weź</Cell></Row>
<Row><Cell>ui_get_xp</Cell><Cell>You improved</Cell><Cell>Udoskonalono</Cell></Row>
<Row><Cell>ui_get_xp_female</Cell><Cell>You've improved</Cell><Cell>Udoskonaliłaś</Cell></Row>
<Row><Cell>ui_help_alchemy_back</Cell><Cell>Back</Cell><Cell>Powrót</Cell></Row>
<Row><Cell>ui_help_alchemy_bellows</Cell><Cell>Bellows</Cell><Cell>Miechy</Cell></Row>
<Row><Cell>ui_help_alchemy_exit</Cell><Cell>Exit</Cell><Cell>Odejdź</Cell></Row>
<Row><Cell>ui_help_alchemy_hourglass</Cell><Cell>Sandglass</Cell><Cell>Klepsydra</Cell></Row>
<Row><Cell>ui_help_alchemy_inventory</Cell><Cell>Inventory</Cell><Cell>Inwentarz</Cell></Row>
<Row><Cell>ui_help_alchemy_reading_autocoo</Cell><Cell>Autobrew</Cell><Cell>Autogotowanie</Cell></Row>
<Row><Cell>ui_help_alchemy_reading_prepare</Cell><Cell>Prepare</Cell><Cell>Przygotuj</Cell></Row>
<Row><Cell>ui_help_alchemy_reading_t_herbs</Cell><Cell>Herbs</Cell><Cell>Zioła</Cell></Row>
<Row><Cell>ui_help_alchemy_reading_t_recip</Cell><Cell>Recipes</Cell><Cell>Przepisy</Cell></Row>
<Row><Cell>ui_help_alchemy_reset</Cell><Cell>Reset</Cell><Cell>Wyczyść</Cell></Row>
<Row><Cell>ui_help_building_outerb</Cell><Cell>Bookmark</Cell><Cell>Zakładka</Cell></Row>
<Row><Cell>ui_help_building_overview</Cell><Cell>Overview</Cell><Cell>Podgląd</Cell></Row>
<Row><Cell>ui_help_building_structure</Cell><Cell>Build</Cell><Cell>Zbuduj</Cell></Row>
<Row><Cell>ui_help_building_upgrade</Cell><Cell>Improvement 1</Cell><Cell>Ulepszenie 1</Cell></Row>
<Row><Cell>ui_help_building_upgrade2</Cell><Cell>Improvement 2</Cell><Cell>Ulepszenie 2</Cell></Row>
<Row><Cell>ui_help_haggling_accept</Cell><Cell>Make offer</Cell><Cell>Złóż ofertę</Cell></Row>
<Row><Cell>ui_help_lockpicking_cursor</Cell><Cell>Cursor</Cell><Cell>Kursor</Cell></Row>
<Row><Cell>ui_help_lockpicking_rotate</Cell><Cell>Rotate lock</Cell><Cell>Obróć zamek</Cell></Row>
<Row><Cell>ui_help_pickpocket_end</Cell><Cell>Stop</Cell><Cell>Stop</Cell></Row>
<Row><Cell>ui_help_pickpocket_hold_to_char</Cell><Cell>Hold to search purse</Cell><Cell>Przytrzymaj, by przeszukać kieszenie</Cell></Row>
<Row><Cell>ui_help_pickpocket_left</Cell><Cell>Left</Cell><Cell>Lewo</Cell></Row>
<Row><Cell>ui_help_pickpocket_right</Cell><Cell>Right</Cell><Cell>Prawo</Cell></Row>
<Row><Cell>ui_help_pickpocket_take</Cell><Cell>Take</Cell><Cell>Weź</Cell></Row>
<Row><Cell>ui_help_pickpocket_uncover</Cell><Cell>Reveal</Cell><Cell>Odsłoń</Cell></Row>
<Row><Cell>ui_help_reading_next</Cell><Cell>Next</Cell><Cell>Następna</Cell></Row>
<Row><Cell>ui_help_reading_prev</Cell><Cell>Previous</Cell><Cell>Poprzednia</Cell></Row>
<Row><Cell>ui_help_reading_study</Cell><Cell>Study</Cell><Cell>Studiuj</Cell></Row>
<Row><Cell>ui_help_skiptime_back</Cell><Cell>Back</Cell><Cell>Powrót</Cell></Row>
<Row><Cell>ui_help_skiptime_cancel</Cell><Cell>Cancel</Cell><Cell>Anuluj</Cell></Row>
<Row><Cell>ui_help_skiptime_down</Cell><Cell>-1 Hour</Cell><Cell> -1 h</Cell></Row>
<Row><Cell>ui_help_skiptime_start</Cell><Cell>Start</Cell><Cell>Rozpocznij</Cell></Row>
<Row><Cell>ui_help_skiptime_up</Cell><Cell>+1 Hour</Cell><Cell> +1 h</Cell></Row>
<Row><Cell>ui_hint_cutscene_abort</Cell><Cell>Skip all</Cell><Cell>Pomiń wszystko</Cell></Row>
<Row><Cell>ui_hint_cutscene_skip</Cell><Cell>Skip part</Cell><Cell>Pomiń tę część</Cell></Row>
<Row><Cell>ui_hint_surrender</Cell><Cell>Surrender</Cell><Cell>Poddaj się</Cell></Row>
<Row><Cell>ui_hold_to</Cell><Cell>Hold to</Cell><Cell>Chwyć</Cell></Row>
<Row><Cell>ui_horse_inspect_back</Cell><Cell>Close</Cell><Cell>Zamknij</Cell></Row>
<Row><Cell>ui_horse_inspect_take</Cell><Cell>Take horse</Cell><Cell>Weź konia</Cell></Row>
<Row><Cell>ui_hud_alchemy_reason</Cell><Cell>This can't be done in the alchemy minigame.</Cell><Cell>Nie można tego wykonać w czasie minigry Alchemia.</Cell></Row>
<Row><Cell>ui_hud_basic_steal</Cell><Cell>Pickpocket</Cell><Cell>Kradnij z kieszeni</Cell></Row>
<Row><Cell>ui_hud_book_start_use</Cell><Cell>Read</Cell><Cell>Czytaj</Cell></Row>
<Row><Cell>ui_hud_book_stop_use</Cell><Cell>Back</Cell><Cell>Powrót</Cell></Row>
<Row><Cell>ui_hud_burn_arrows</Cell><Cell>Set arrows alight</Cell><Cell>Zapal strzały</Cell></Row>
<Row><Cell>ui_hud_burn_hay</Cell><Cell>Set hay on fire.</Cell><Cell>Podpal siano</Cell></Row>
<Row><Cell>ui_hud_burn_herbs</Cell><Cell>Burn the herbs</Cell><Cell>Spal zioła</Cell></Row>
<Row><Cell>ui_hud_bury</Cell><Cell>Bury</Cell><Cell>Pochowaj</Cell></Row>
<Row><Cell>ui_hud_cantReadHere</Cell><Cell>You can't read here.</Cell><Cell>Tutaj nie możesz czytać.</Cell></Row>
<Row><Cell>ui_hud_caption_object_admire</Cell><Cell>Admire</Cell><Cell>Podziwiaj</Cell></Row>
<Row><Cell>ui_hud_caption_object_read</Cell><Cell>Read</Cell><Cell>Czytaj</Cell></Row>
<Row><Cell>ui_hud_carry_corpse_reason</Cell><Cell>This can't be done while you're carrying someone.</Cell><Cell>Nie możesz tego zrobić, jeśli kogoś niesiesz.</Cell></Row>
<Row><Cell>ui_hud_crawl_through_window</Cell><Cell>Crawl through window</Cell><Cell>Przejdź się przez okno</Cell></Row>
<Row><Cell>ui_hud_dash</Cell><Cell>Gallop</Cell><Cell>Galop</Cell></Row>
<Row><Cell>ui_hud_dismount</Cell><Cell>Dismount</Cell><Cell>Zsiądź</Cell></Row>
<Row><Cell>ui_hud_examine</Cell><Cell>Examine</Cell><Cell>Sprawdź</Cell></Row>
<Row><Cell>ui_hud_fail</Cell><Cell>Fail</Cell><Cell>Porażka</Cell></Row>
<Row><Cell>ui_hud_fill_jug</Cell><Cell>Fill jug</Cell><Cell>Napełnij dzban</Cell></Row>
<Row><Cell>ui_hud_get_food</Cell><Cell>Fetch the wine and bacon.</Cell><Cell>Przynieś wino i boczek.</Cell></Row>
<Row><Cell>ui_hud_get_water</Cell><Cell>Get water</Cell><Cell>Przynieś wodę</Cell></Row>
<Row><Cell>ui_hud_grab</Cell><Cell>Grab body</Cell><Cell>Weź ciało</Cell></Row>
<Row><Cell>ui_hud_hide_out</Cell><Cell>Hide</Cell><Cell>Ukryj</Cell></Row>
<Row><Cell>ui_hud_horse_inspect</Cell><Cell>Inspect horse</Cell><Cell>Sprawdź konia</Cell></Row>
<Row><Cell>ui_hud_horse_pulldown</Cell><Cell>Unhorse</Cell><Cell>Ściągnij z konia</Cell></Row>
<Row><Cell>ui_hud_hunt_attack</Cell><Cell>Tackle</Cell><Cell>Zatrzymaj</Cell></Row>
<Row><Cell>ui_hud_chair_getup</Cell><Cell>Get up</Cell><Cell>Wstań</Cell></Row>
<Row><Cell>ui_hud_indulgence_notEnoughMoney</Cell><Cell>You can't afford this.</Cell><Cell>Nie stać cię na to.</Cell></Row>
<Row><Cell>ui_hud_indulgence_part1</Cell><Cell>Pay indulgence:</Cell><Cell>Zapłać za odpust:</Cell></Row>
<Row><Cell>ui_hud_indulgence_part2</Cell><Cell>Gr.</Cell><Cell>Gr.</Cell></Row>
<Row><Cell>ui_hud_inspect_corpse</Cell><Cell>Inspect</Cell><Cell>Zbadaj</Cell></Row>
<Row><Cell>ui_hud_inspect_item</Cell><Cell>Inspect</Cell><Cell>Zbadaj</Cell></Row>
<Row><Cell>ui_hud_inspect_kettle</Cell><Cell>Inspect cauldron</Cell><Cell>Sprawdź kociołek</Cell></Row>
<Row><Cell>ui_hud_judge</Cell><Cell>Judge</Cell><Cell>Osądź</Cell></Row>
<Row><Cell>ui_hud_jump</Cell><Cell>Jump</Cell><Cell>Skok</Cell></Row>
<Row><Cell>ui_hud_knock_item</Cell><Cell>Knock</Cell><Cell>Zapukaj</Cell></Row>
<Row><Cell>ui_hud_knock_out</Cell><Cell>Knock out</Cell><Cell>Znokautuj</Cell></Row>
<Row><Cell>ui_hud_knockOnDoor</Cell><Cell>Knock on door</Cell><Cell>Zapukaj do drzwi</Cell></Row>
<Row><Cell>ui_hud_lockpick</Cell><Cell>Lockpick</Cell><Cell>Włam się</Cell></Row>
<Row><Cell>ui_hud_lockpick_difficulty_1</Cell><Cell>Lockpick (very easy)</Cell><Cell>Włamywanie (bardzo łatwe)</Cell></Row>
<Row><Cell>ui_hud_lockpick_difficulty_2</Cell><Cell>Lockpick (easy)</Cell><Cell>Włamywanie (łatwe)</Cell></Row>
<Row><Cell>ui_hud_lockpick_difficulty_3</Cell><Cell>Lockpick (hard)</Cell><Cell>Włamywanie (trudne)</Cell></Row>
<Row><Cell>ui_hud_lockpick_difficulty_4</Cell><Cell>Lockpick (very hard)</Cell><Cell>Włamywanie (bardzo trudne)</Cell></Row>
<Row><Cell>ui_hud_loot</Cell><Cell>Loot</Cell><Cell>Łup</Cell></Row>
<Row><Cell>ui_hud_mercy_kill</Cell><Cell>Mercy kill</Cell><Cell>Cios Miłosierdzia</Cell></Row>
<Row><Cell>ui_hud_mercy_kill_unconscious</Cell><Cell>Kill</Cell><Cell>Zabij</Cell></Row>
<Row><Cell>ui_hud_mount</Cell><Cell>Mount</Cell><Cell>Wsiądź</Cell></Row>
<Row><Cell>ui_hud_mount_and_steal</Cell><Cell>Mount and steal</Cell><Cell>Dosiądź konia i ukradnij</Cell></Row>
<Row><Cell>ui_hud_move_to_chest</Cell><Cell>Put items in trunk</Cell><Cell>Włóż przedmioty do skrzyni</Cell></Row>
<Row><Cell>ui_hud_pick_up_ptacek</Cell><Cell>Pick up Capon</Cell><Cell>Zabierz Ptaszka</Cell></Row>
<Row><Cell>ui_hud_pickpocket_fail_detected_by_victim</Cell><Cell>You were caught in the act by your victim.</Cell><Cell>Twoja ofiara złapała cię na gorącym uczynku.</Cell></Row>
<Row><Cell>ui_hud_pickpocket_fail_lost</Cell><Cell>Your victim got away.</Cell><Cell>Twoja ofiara uciekła.</Cell></Row>
<Row><Cell>ui_hud_pickpocket_fail_seen_by_someone</Cell><Cell>You were seen by a witness.</Cell><Cell>Widział cię świadek.</Cell></Row>
<Row><Cell>ui_hud_play_dice</Cell><Cell>Play dice</Cell><Cell>Zagraj w kości</Cell></Row>
<Row><Cell>ui_hud_poisonWine</Cell><Cell>Poison wine</Cell><Cell>Zatruj wino.</Cell></Row>
<Row><Cell>ui_hud_put</Cell><Cell>Drop  </Cell><Cell>Odłóż </Cell></Row>
<Row><Cell>ui_hud_put_herbs</Cell><Cell>Add the herbs</Cell><Cell>Dodaj zioła</Cell></Row>
<Row><Cell>ui_hud_read</Cell><Cell>Read</Cell><Cell>Czytaj</Cell></Row>
<Row><Cell>ui_hud_reputation_notification_crime_reported</Cell><Cell>Crime reported</Cell><Cell>Zgłoszone Przestępstwo</Cell></Row>
<Row><Cell>ui_hud_reputation_notification_reputation_gained</Cell><Cell>Reputation gained</Cell><Cell>Wzrost Reputacji</Cell></Row>
<Row><Cell>ui_hud_reputation_notification_reputation_lost</Cell><Cell>Reputation lost</Cell><Cell>Spadek Reputacji</Cell></Row>
<Row><Cell>ui_hud_saddle_horse</Cell><Cell>Saddle horse</Cell><Cell>Osiodłaj konia</Cell></Row>
<Row><Cell>ui_hud_scareHorse</Cell><Cell>Stampede horse</Cell><Cell>Wypłosz konia</Cell></Row>
<Row><Cell>ui_hud_sharpening_less_pressure</Cell><Cell>Less pressure</Cell><Cell>Mniejszy nacisk</Cell></Row>
<Row><Cell>ui_hud_sharpening_more_pressure</Cell><Cell>More pressure</Cell><Cell>Większy nacisk</Cell></Row>
<Row><Cell>ui_hud_sharpening_position</Cell><Cell>Position</Cell><Cell>Pozycja</Cell></Row>
<Row><Cell>ui_hud_sharpening_pressure</Cell><Cell>Pressure</Cell><Cell>Nacisk</Cell></Row>
<Row><Cell>ui_hud_sharpening_rotation</Cell><Cell>Angle</Cell><Cell>Nachylenie</Cell></Row>
<Row><Cell>ui_hud_sharpening_step</Cell><Cell>Pedal</Cell><Cell>Naciśnij pedał</Cell></Row>
<Row><Cell>ui_hud_sit</Cell><Cell>Sit</Cell><Cell>Usiądź</Cell></Row>
<Row><Cell>ui_hud_sitting_action_exit</Cell><Cell>Get up</Cell><Cell>Wstań</Cell></Row>
<Row><Cell>ui_hud_sitting_action_inventory</Cell><Cell>Inventory</Cell><Cell>Inwentarz</Cell></Row>
<Row><Cell>ui_hud_sitting_action_sleep</Cell><Cell>Sleep</Cell><Cell>Śpij</Cell></Row>
<Row><Cell>ui_hud_sitting_reason</Cell><Cell>This can't be done while sitting.</Cell><Cell>Nie można tego zrobić, jeśli siedzisz.</Cell></Row>
<Row><Cell>ui_hud_SkipDialog</Cell><Cell>Cancel</Cell><Cell>Anuluj</Cell></Row>
<Row><Cell>ui_hud_sleep</Cell><Cell>Sleep</Cell><Cell>Śpij</Cell></Row>
<Row><Cell>ui_hud_sleep_and_save</Cell><Cell>Sleep and save</Cell><Cell>Sen i zapis</Cell></Row>
<Row><Cell>ui_hud_start_alchemy</Cell><Cell>Start alchemy</Cell><Cell>Zacznij z Alchemią</Cell></Row>
<Row><Cell>ui_hud_start_digging</Cell><Cell>Start digging</Cell><Cell>Zacznij kopać</Cell></Row>
<Row><Cell>ui_hud_start_transcribing</Cell><Cell>Start transcribing</Cell><Cell>Zacznij przepisywać</Cell></Row>
<Row><Cell>ui_hud_start_use</Cell><Cell>Start using</Cell><Cell>Zacznij używać</Cell></Row>
<Row><Cell>ui_hud_stealItem</Cell><Cell>Steal</Cell><Cell>Ukradnij</Cell></Row>
<Row><Cell>ui_hud_stealth_kill</Cell><Cell>Stealth kill</Cell><Cell>Kradzież, Zabij</Cell></Row>
<Row><Cell>ui_hud_stop_use</Cell><Cell>Stop</Cell><Cell>Przerwij</Cell></Row>
<Row><Cell>ui_hud_succes</Cell><Cell>Success</Cell><Cell>Sukces</Cell></Row>
<Row><Cell>ui_hud_take</Cell><Cell>Take</Cell><Cell>Weź</Cell></Row>
<Row><Cell>ui_hud_talk</Cell><Cell>Talk</Cell><Cell>Rozmawiaj</Cell></Row>
<Row><Cell>ui_hud_throw_dice</Cell><Cell>Throw dice</Cell><Cell>Rzuć kostkami</Cell></Row>
<Row><Cell>ui_hud_treat</Cell><Cell>Treat</Cell><Cell>Opatrz </Cell></Row>
<Row><Cell>ui_hud_unlock</Cell><Cell>Unlock</Cell><Cell>Otwórz zamek</Cell></Row>
<Row><Cell>ui_hud_untie</Cell><Cell>Untie</Cell><Cell>Rozwiąż</Cell></Row>
<Row><Cell>ui_hud_use_grindstone</Cell><Cell>Start</Cell><Cell>Użyj brusu</Cell></Row>
<Row><Cell>ui_hud_use_item</Cell><Cell>Use</Cell><Cell>Użyj</Cell></Row>
<Row><Cell>ui_hud_use_item_sabotage</Cell><Cell>Sabotage</Cell><Cell>Sabotuj</Cell></Row>
<Row><Cell>ui_hud_wait</Cell><Cell>Wait</Cell><Cell>Poczekaj</Cell></Row>
<Row><Cell>ui_hud_you_cant_call_dog</Cell><Cell>You can't give commands to your dog now.</Cell><Cell>Teraz nie możesz rozkazywać swemu psu.</Cell></Row>
<Row><Cell>ui_hud_you_discovered</Cell><Cell>You discovered</Cell><Cell>Odkryłeś:</Cell></Row>
<Row><Cell>ui_hud_you_discovered_female</Cell><Cell>You discovered</Cell><Cell>Odkryłaś</Cell></Row>
<Row><Cell>ui_hud_you_learned</Cell><Cell>You learned</Cell><Cell>Nauczyłeś się:</Cell></Row>
<Row><Cell>ui_hud_you_learned_female</Cell><Cell>You learned</Cell><Cell>Nauczyłaś się</Cell></Row>
<Row><Cell>ui_in_alchem_flag_alcohol</Cell><Cell>spirits</Cell><Cell>Alkohol</Cell></Row>
<Row><Cell>ui_in_alchem_flag_bellows</Cell><Cell>bellows</Cell><Cell>Miech</Cell></Row>
<Row><Cell>ui_in_alchem_flag_book</Cell><Cell>book</Cell><Cell>Książka</Cell></Row>
<Row><Cell>ui_in_alchem_flag_dish</Cell><Cell>dish</Cell><Cell>Naczynie</Cell></Row>
<Row><Cell>ui_in_alchem_flag_distillator</Cell><Cell>still</Cell><Cell>Destylator</Cell></Row>
<Row><Cell>ui_in_alchem_flag_empty_glass</Cell><Cell>phial</Cell><Cell>Przygotuj eliksir</Cell></Row>
<Row><Cell>ui_in_alchem_flag_hourglass</Cell><Cell>sandglass</Cell><Cell>Klepsydra</Cell></Row>
<Row><Cell>ui_in_alchem_flag_kettle</Cell><Cell>cauldron</Cell><Cell>Kociołek</Cell></Row>
<Row><Cell>ui_in_alchem_flag_mortar</Cell><Cell>mortar</Cell><Cell>Moździerz</Cell></Row>
<Row><Cell>ui_in_alchem_flag_oil</Cell><Cell>oil</Cell><Cell>Olej</Cell></Row>
<Row><Cell>ui_in_alchem_flag_pestle</Cell><Cell>pestle</Cell><Cell>Moździerz</Cell></Row>
<Row><Cell>ui_in_alchem_flag_water</Cell><Cell>water</Cell><Cell>Woda</Cell></Row>
<Row><Cell>ui_in_alchem_flag_wine</Cell><Cell>wine</Cell><Cell>Wino</Cell></Row>
<Row><Cell>ui_in_platinum</Cell><Cell>Collect all trophies</Cell><Cell>Zbierz wszystkie trofea.</Cell></Row>
<Row><Cell>ui_in_woodenSword</Cell><Cell>Wooden training sword.</Cell><Cell>Drewniany miecz treningowy</Cell></Row>
<Row><Cell>ui_info_dice_giveup</Cell><Cell>Hold to quit this dice game.</Cell><Cell>Przytrzymaj, jeśli chcesz opuścić tę grę w kości.</Cell></Row>
<Row><Cell>ui_inv_inventory</Cell><Cell>Inventory</Cell><Cell>Inwentarz</Cell></Row>
<Row><Cell>ui_inv_npc</Cell><Cell>NPC</Cell><Cell>NPC</Cell></Row>
<Row><Cell>ui_inv_quest</Cell><Cell>Quest</Cell><Cell>Zadanie</Cell></Row>
<Row><Cell>ui_inv_questTrackedCount</Cell><Cell>($x; )</Cell><Cell>($x; )</Cell></Row>
<Row><Cell>ui_inv_store</Cell><Cell>Found</Cell><Cell>Znajdź</Cell></Row>
<Row><Cell>ui_loading_hint_1</Cell><Cell>If you want to know what's going on in the vicinity or find out if anyone needs your help, it's best to ask the local innkeeper, who's sure to know all the local gossip.
</Cell><Cell>Jeśli chcesz się dowiedzieć, co się dzieje w okolicy lub czy ktoś nie potrzebuje twojej pomocy, najlepiej spytać miejscowego oberżysty, który zna wszystkie plotki.</Cell></Row>
<Row><Cell>ui_loading_hint_10</Cell><Cell>If you want to try your hand at gambling, it’s possible to play the dice game of Farkle in every respectable tavern.</Cell><Cell>Jeżeli lubisz ryzyko, w każdej karczmie możesz zagrać w kości.</Cell></Row>
<Row><Cell>ui_loading_hint_11</Cell><Cell>Alchemy is a useful skill that transforms herbs and other ingredients into potions and remedies. In order to brew those, you need a knowledge of alchemy, a recipe, an alchemist’s bench and the necessary ingredients.
</Cell><Cell>Alchemia to przydatna umiejętność przetwarzania ziół i innych składników w eliksiry i leki. Aby je przygotować, musisz zdobyć wiedzę nt. alchemii, zyskać przepisy, niezbędne ingrediencje i dotrzeć do laboratorium.</Cell></Row>
<Row><Cell>ui_loading_hint_12</Cell><Cell>Once you’ve become skilled enough at alchemy, you’ll have the option of auto-brewing potions.</Cell><Cell>Jak tylko wprawisz się w alchemii, będziesz mógł korzystać z opcji autogotowania eliksirów.</Cell></Row>
<Row><Cell>ui_loading_hint_13</Cell><Cell>Bleeding is a specific type of injury. If you're bleeding, you must quickly bandage the wound, otherwise you'll soon bleed out and die.
</Cell><Cell>Specyficznym typem urazu jest krwawienie. Jeśli krwawisz, trzeba szybko obwiązać ranę, bo inaczej możesz się wykrwawić i wkrótce umrzeć.</Cell></Row>
<Row><Cell>ui_loading_hint_14</Cell><Cell>Keep in mind that during combat it is not possible to heal yourself!   
</Cell><Cell>I pamiętaj, że w trakcie walki nie ma możliwości leczenia się!</Cell></Row>
<Row><Cell>ui_loading_hint_15</Cell><Cell>If you want to maintain bladed weapons, you can save your repair kit and hone them yourself on a grinding wheel, which you can find at every smithy.
</Cell><Cell>Jeżeli chcesz, aby twoja broń pozostała ostra, nie musisz używać swego niezbędnika do naprawy. W każdej kuźni znajdziesz brus, na którym możesz sam wyszlifować swoje ostrze.</Cell></Row>
<Row><Cell>ui_loading_hint_16</Cell><Cell>Life is God’s gift and combat doesn’t always have to end in death! So when it’s clear that a combatant is beaten, he always has the option to surrender honourably, and the honourable response is to accept his surrender.
</Cell><Cell>Żywot to dar od Boga i walka nie zawsze musi zakończyć się śmiercią! Kiedy to jasne, że wojownik jest pokonany, zawsze istnieje opcja honorowego poddania się i równie honorowa odpowiedź w postaci przyjęcia tego poddania.</Cell></Row>
<Row><Cell>ui_loading_hint_17</Cell><Cell>If a guard, catchpole or other figure of authority challenges you to surrender or to agree to a personal search, you can do so. But you’d better decide quick, because the guardians of the law have little patience in these troubled times and they won’t hesitate to use force if you don’t cooperate.
</Cell><Cell>Kiedy straż lub inne uprawnione postacie zażądają, abyś się poddał lub zgodził się na rewizję osobistą, możesz to zrobić. Musisz jednak szybko się zdecydować, ponieważ strażnicy w tych czasach nie mają zbyt wiele cierpliwości i nie zawahają się przed użyciem siły, by wymusić swoje żądania.</Cell></Row>
<Row><Cell>ui_loading_hint_18</Cell><Cell>In order to pickpocket someone successfully, you first have to sneak up on them unnoticed.
</Cell><Cell>Aby kogoś obrabować, musisz najpierw podejść niezauważony.</Cell></Row>
<Row><Cell>ui_loading_hint_19</Cell><Cell>If you want to store things to use later, you can put them in the trunk you'll find at any of your assigned or rented sleeping places. The same items can be found in all the trunks you have.
</Cell><Cell>Jeśli chcesz przechować rzeczy na później, możesz je włożyć do skrzyni w kupionym czy wynajętym miejscu noclegowym. We wszystkich skrzyniach, które posiadasz, znajdziesz te same przedmioty.</Cell></Row>
<Row><Cell>ui_loading_hint_2</Cell><Cell>The Codex accumulates all information about the world, points of interest and detailed tutorials.
</Cell><Cell>Kodeks zawiera wszystkie informacje o świecie, interesujących miejscach oraz szczegółowe instrukcje.</Cell></Row>
<Row><Cell>ui_loading_hint_20</Cell><Cell>You can skip time and wait for something. If you’re in the middle of some activity, however, the Skip Time button will call up Help.
</Cell><Cell>Możesz przyspieszyć czas i skrócić czekanie na coś. Jeśli jesteś w trakcie jakiejś czynności, przycisk Przyspiesz czas włączy Pomoc.</Cell></Row>
<Row><Cell>ui_loading_hint_21</Cell><Cell>If your loot is really hot, it’s best to go to a known fence. For example, the millers have a reputation for being mixed up in shady deals.</Cell><Cell>Jeśli twój łup jest bardzo pożądany, lepiej sprzedaj go w sprawdzonym miejscu, np. u młynarzy. Są znani z mieszania się w ciemne interesy.</Cell></Row>
<Row><Cell>ui_loading_hint_22</Cell><Cell>While brewing potions it’s always best to follow the recipe in the book. You can also easily set all the necessary ingredients straight onto the alchemy bench.</Cell><Cell>Gdy przygotowujesz eliksiry, lepiej zawsze trzymać się przepisu w księdze. Możesz także od razu wyłożyć na stół wszystkie potrzebne ingrediencje.</Cell></Row>
<Row><Cell>ui_loading_hint_23</Cell><Cell>No one is born a master swordsman. It takes practice. Captain Bernard will show you the basics at the start, but to achieve mastery you'll have to visit him repeatedly.</Cell><Cell>Nikt od razu nie włada mieczem po mistrzowsku. To wymaga praktyki. Kapitan Bernard nauczy cię podstaw, ale by osiągnąć wprawę, będziesz musiał przyjść do niego kilka razy.</Cell></Row>
<Row><Cell>ui_loading_hint_24</Cell><Cell>If you find yourself heavily outnumbered, the best option may be "run away - live to fight another day". You can always come back when you're more skilled at combat, more stealthy or fortified with potions.</Cell><Cell>W sytuacji, gdy przeciwnik ma przewagę liczebną, najlepiej będzie, jeśli uciekniesz i przełożysz walkę na kiedy indziej. Zawsze możesz do niej wrócić, kiedy udoskonalisz się w boju, skradaniu się czy używaniu eliksirów.</Cell></Row>
<Row><Cell>ui_loading_hint_25</Cell><Cell>If you end up on the wrong side of the law, it's best to save your reputation by submitting to arrest and cleansing your soul with a little jail time.</Cell><Cell>Jeżeli przekroczysz granice prawa, lepiej zadbaj o swoją Reputację i pozwól się pojmać, oczyszczając swoje imię pobytem w więzieniu.</Cell></Row>
<Row><Cell>ui_loading_hint_26</Cell><Cell>Even if you're not caught red-handed, your crimes will make people bad-tempered, and angry guards are more likely to stop and search you, angry traders to be less willing to haggle.</Cell><Cell>Nawet jeśli nie zostaniesz schwytany na gorącym uczynku, twoje przestępstwa mogą zrazić ludzi do ciebie. Wściekli strażnicy częściej będą cię zatrzymywać i sprawdzać, a kupcy niechętnie będą się targować.</Cell></Row>
<Row><Cell>ui_loading_hint_27</Cell><Cell>There are big differences between horses. A new one costs a lot, but it's a worthwhile investment - not just to get around faster, but also to carry a heavier load.</Cell><Cell>Konie bardzo różnią się od siebie. Nowy sporo kosztuje, ale jest wart swej ceny. Nie tylko porusza się szybciej, ale także poniesie cięższy ładunek.</Cell></Row>
<Row><Cell>ui_loading_hint_28</Cell><Cell>Even your finest clothing can lose it's charm if hidden beneath battered armour or a layer of dirt and blood.</Cell><Cell>Nawet twoje najlepsze ubranie straci swój urok, jeśli przykryje je obtłuczona zbroja, warstwa brudu czy krwi.</Cell></Row>
<Row><Cell>ui_loading_hint_29</Cell><Cell>Theresa acquires and improves skills just like Henry, but some will not be available to her in Skalitz, such as horse-riding, alchemy and pickpocketing. These skills have a zero value in the character's stats.</Cell><Cell>Teresa zdobywa i rozwija Umiejętności podobnie jak Henryk, ale w Skalicy część z nich może być dla niej niedostępna, np. Jazda konna, Alchemia lub Drobna kradzież. Poziom takich Umiejętności jest równy zeru.</Cell></Row>
<Row><Cell>ui_loading_hint_3</Cell><Cell>Every unsuccessful bout of haggling lowers your reputation with the trader. On the contrary, if you tip the trader or give him or her a discount, your reputation will improve.
</Cell><Cell>Każda niepomyślna transakcja pogorszy twoją Reputację wśród handlarzy. Z drugiej strony, gdy w czasie targowania się dasz komuś napiwek lub obniżysz cenę, twoja Reputacja się polepszy.</Cell></Row>
<Row><Cell>ui_loading_hint_30</Cell><Cell>Theresa does not acquire perk points, but you can unlock new perks for her by completing certain objectives.</Cell><Cell>Teresa nie otrzymuje punktów dodatkowych, ale można odblokować dla niej nowe Dodatki, wykonując pewne zadania.</Cell></Row>
<Row><Cell>ui_loading_hint_31</Cell><Cell>There's no cross-dressing in the middle ages! Just as Henry cannot put on women's clothes, neither can Theresa wear men's.</Cell><Cell>W średniowieczu ubierano się zgodnie z przynależnością do płci! Henryk nie założyłby damskiego ubrania, a Teresa męskiego.</Cell></Row>
<Row><Cell>ui_loading_hint_32</Cell><Cell>Theresa is accompanied everywhere by her faithful dog, Tinker, who can help her in combat, tracking people and sniffing out interesting things.</Cell><Cell>Teresie towarzyszy wierny pies, Bies, który może jej pomóc w walce, tropiąc ludzi lub znajdując interesujące rzeczy.</Cell></Row>
<Row><Cell>ui_loading_hint_33</Cell><Cell>Skalitz is a small but important settlement with a castle, which gets its prestige from the local silver mines. All the silver belongs to the king.</Cell><Cell>Skalica to mała, ale ważna osada. Znajduje się w niej zamek, a prestiż tej miejscowości podnosi obecność kopalni srebra. Srebro w całości należy do króla.</Cell></Row>
<Row><Cell>ui_loading_hint_34</Cell><Cell>Theresa is capable of wielding a weapon, but that doesn't make her a warrior. It's usually best to find another way to resolve conflicts.</Cell><Cell>Teresa potrafi władać bronią, ale to jeszcze nie czyni z niej wojownika. Lepiej, aby w inny sposób rozwiązywała konflikty.</Cell></Row>
<Row><Cell>ui_loading_hint_35</Cell><Cell>Work at the mines is tough, but not only men do it. In the sorting plant where the ore is separated, it is mostly women who do the work.</Cell><Cell>Praca w kopalni jest ciężka, ale mogą ją wykonywać nie tylko mężczyźni. Sortowaniem rudy zajmują się głównie kobiety.</Cell></Row>
<Row><Cell>ui_loading_hint_4</Cell><Cell>If you need a light at night, use your torch.
</Cell><Cell>Jeżeli potrzebujesz w nocy światła, użyj swej pochodni.</Cell></Row>
<Row><Cell>ui_loading_hint_5</Cell><Cell>You also need to watch what you eat – if you eat or drink something that’s spoiled, you can get food poisoning, which you can only cure by taking Digestive potion. You can tell you’ve been poisoned by the icon next to your health indicator.
</Cell><Cell>Musisz też uważać na to, co jesz. Jeżeli zjesz czy wypijesz coś zepsutego, możesz dostać Zatrucia pokarmowego. Wówczas wyleczy cię tylko eliksir Na trawienie. O zatruciu dowiesz się dzięki ikonce tuż przy wskaźniku twojego Zdrowia.</Cell></Row>
<Row><Cell>ui_loading_hint_6</Cell><Cell>Reading was a rare skill in the middle ages and a common blacksmith's son certainly wouldn't have been literate. If you want to learn to read, you need to find someone who'll teach you.
</Cell><Cell>Niewiele osób w średniowieczu potrafiło czytać i z pewnością nie należał do nich zwykły syn kowala. Jeżeli chcesz posiąść tę umiejętność, musisz znaleźć kogoś, kto cię tego nauczy.</Cell></Row>
<Row><Cell>ui_loading_hint_7</Cell><Cell>When you’re dirty, you don’t have to rush immediately to the nearest bathhouse – you can have a quick wash at the nearest water trough.
</Cell><Cell>Jeśli jesteś brudny, nie musisz od razu biec do najbliższej łaźni. Możesz się obmyć w najbliższej balii czy korycie z wodą.</Cell></Row>
<Row><Cell>ui_loading_hint_8</Cell><Cell>In these harsh times, people are wary of anything out of the ordinary. If you step inside someone's house uninvited, for example, they will first warn you that you've no business there, but if you do anything untoward there, they will immediately call for a guard.</Cell><Cell>W tych ciężkich czasach ludzie są szczególnie bojaźliwi i nieufni. Jeśli na przykład nieproszony wejdziesz do czyjegoś domu, najpierw zostaniesz ostrzeżony, że nie masz tam czego szukać. Ale gdy zrobisz coś niestosownego, natychmiast wezwą straż.</Cell></Row>
<Row><Cell>ui_loading_hint_9</Cell><Cell>Alcohol is a useful thing, but it's also the scourge of mankind and a good Christian should avoid it like the plague.</Cell><Cell>Alkohol to przekleństwo ludzkości i dobry chrześcijanin powinien unikać go jak ognia.</Cell></Row>
<Row><Cell>ui_mod_removal_items</Cell><Cell>It seems you have uninstalled a mod that added new content (items, NPCs, perks etc.) and this content has been deleted in the process.</Cell><Cell>Prawdopodobnie odinstalowano modyfikację a wraz z nią usunięto dodatkowe przedmioty, NPC, perki itd., które się w niej znajdowały.</Cell></Row>
<Row><Cell>ui_new_homes_missing_prerequisities</Cell><Cell>Prerequisites lacking</Cell><Cell>Brakujące zasoby</Cell></Row>
<Row><Cell>ui_new_horse</Cell><Cell>Other horse</Cell><Cell>Inny koń</Cell></Row>
<Row><Cell>ui_new_perkpoint</Cell><Cell>New perk point available</Cell><Cell>Dostępne są nowe punkty za Dodatki.</Cell></Row>
<Row><Cell>ui_nh_base_structure_stats</Cell><Cell>Basic structure</Cell><Cell>Podstawowy budynek</Cell></Row>
<Row><Cell>ui_nm_platinum</Cell><Cell>Platinum Trophy</Cell><Cell>Platynowe Trofeum</Cell></Row>
<Row><Cell>ui_nm_woodenSword</Cell><Cell>Wooden sword</Cell><Cell>Drewniany miecz</Cell></Row>
<Row><Cell>ui_north_shortcut</Cell><Cell>N</Cell><Cell>N</Cell></Row>
<Row><Cell>ui_northeast_shortcut</Cell><Cell>NE</Cell><Cell>NE</Cell></Row>
<Row><Cell>ui_northwest_shortcut</Cell><Cell>NW</Cell><Cell>NW</Cell></Row>
<Row><Cell>ui_objectiveCompleteHintDefault</Cell><Cell>Objective completed: </Cell><Cell>Cel osiągnięty:</Cell></Row>
<Row><Cell>ui_objectiveFailHintDefault</Cell><Cell>Objective failed: </Cell><Cell>Cel nieosiągnięty:</Cell></Row>
<Row><Cell>ui_objectiveStartHintDefault</Cell><Cell>Objective started: </Cell><Cell>Rozpoczęty cel:</Cell></Row>
<Row><Cell>ui_objectiveUpdatedHintDefault</Cell><Cell>Objective updated</Cell><Cell>Cel zaktualizowany:</Cell></Row>
<Row><Cell>ui_open_nest</Cell><Cell>Examine nest</Cell><Cell>Zbadaj gniazdo</Cell></Row>
<Row><Cell>ui_open_stash</Cell><Cell>Open</Cell><Cell>Otwórz</Cell></Row>
<Row><Cell>ui_open_stash_crime</Cell><Cell>Rob</Cell><Cell>Kradnij</Cell></Row>
<Row><Cell>ui_pay</Cell><Cell>pay</Cell><Cell>Zapłać</Cell></Row>
<Row><Cell>ui_Pdg</Cell><Cell>Pidgen English</Cell><Cell>PDG Angielski</Cell></Row>
<Row><Cell>ui_perk_activeted</Cell><Cell>You activated the perk</Cell><Cell>Aktywowano dodatek:</Cell></Row>
<Row><Cell>ui_perk_sixthSense</Cell><Cell>You've been seen!</Cell><Cell>Widziano cię!</Cell></Row>
<Row><Cell>ui_perk_used</Cell><Cell>You used the perk</Cell><Cell>Użyto dodatek:</Cell></Row>
<Row><Cell>ui_pickHerb</Cell><Cell>Gather</Cell><Cell>Zbierz</Cell></Row>
<Row><Cell>ui_pickpocket_failed</Cell><Cell>Pickpocketing failed</Cell><Cell>Kradzież nie powiodła się.</Cell></Row>
<Row><Cell>ui_pickpocket_suceeded</Cell><Cell>Pickpocketing successful</Cell><Cell>Powiodła ci się drobna kradzież</Cell></Row>
<Row><Cell>ui_pickup_item</Cell><Cell>Pick up</Cell><Cell>Podnieś</Cell></Row>
<Row><Cell>ui_playerCantSkipTime_combat</Cell><Cell>You can't skip time while in combat.</Cell><Cell>Nie możesz przyspieszyć czasu w trakcie walki.</Cell></Row>
<Row><Cell>ui_playerCantSkiptime_lowFood</Cell><Cell>You're too hungry!</Cell><Cell>Jesteś zbyt głodny!</Cell></Row>
<Row><Cell>ui_playerCantSkiptime_lowHealth</Cell><Cell>You're too badly hurt, you need treatment.</Cell><Cell>Jesteś poważnie ranny, wymagasz leczenia.</Cell></Row>
<Row><Cell>ui_playerCantSkiptime_timePause</Cell><Cell>You can't delay - no time to lose!</Cell><Cell>Nie możesz teraz opóźniać! Nie ma czasu do stracenia!</Cell></Row>
<Row><Cell>ui_playerCantSleep</Cell><Cell>You can't sleep right now.</Cell><Cell>Nie możesz teraz spać.</Cell></Row>
<Row><Cell>ui_playerCantSleep_combat</Cell><Cell>You can't sleep while you're in a fight.</Cell><Cell>Nie możesz spać w trakcie walki.</Cell></Row>
<Row><Cell>ui_playerCantSleep_lowFood</Cell><Cell>You're too hungry to sleep.</Cell><Cell>Jesteś zbyt głodny, żeby spać.</Cell></Row>
<Row><Cell>ui_playerCantSleep_lowHealth</Cell><Cell>You're too badly wounded to sleep. Heal yourself!</Cell><Cell>Jesteś zraniony i nie możesz spać. </Cell></Row>
<Row><Cell>ui_playerCantSleep_oversleep</Cell><Cell>You can't fall asleep because you've slept too long already.</Cell><Cell>Nie możesz zasnąć, ponieważ spałeś już dostatecznie długo.</Cell></Row>
<Row><Cell>ui_playerCantSleep_timePaused</Cell><Cell>You can't sleep because the world time is paused.</Cell><Cell>Nie możesz spać, ponieważ czas we świecie został zatrzymany.</Cell></Row>
<Row><Cell>ui_playerCantStudy_bookIsFinish</Cell><Cell>You've already read this book from cover to cover.</Cell><Cell>Przeczytałeś już tę książkę „od deski do deski“.</Cell></Row>
<Row><Cell>ui_playerCantStudy_lowReading</Cell><Cell>You don't have the reading skill needed to read this book.</Cell><Cell>Jeszcze nie masz opanowanej umiejętności czytania, by przeczytać tę książkę.</Cell></Row>
<Row><Cell>ui_playerCantStudy_lowSkill</Cell><Cell>You haven't reached the skill level needed to be able to use this book.</Cell><Cell>Jeszcze nie osiągnąłeś takiej wprawy w czytaniu, abyś mógł skorzystać z tej książki.</Cell></Row>
<Row><Cell>ui_playerCantStudy_overread</Cell><Cell>You can't focus on reading anymore - you've read enough today.</Cell><Cell>Nie możesz już więcej skupić się na czytaniu, dziś dość już przeczytałeś.</Cell></Row>
<Row><Cell>ui_players_horse</Cell><Cell>My horse</Cell><Cell>Mój koń</Cell></Row>
<Row><Cell>ui_put_into_kettle</Cell><Cell>Drop into pot</Cell><Cell>Wrzuć do garnka.</Cell></Row>
<Row><Cell>ui_q_nightsWatch_interrupt</Cell><Cell>Interrupt argument</Cell><Cell>Przerwij argumentem</Cell></Row>
<Row><Cell>ui_questCompleted</Cell><Cell>Quest completed</Cell><Cell>Zadanie wykonane</Cell></Row>
<Row><Cell>ui_questFailed</Cell><Cell>Quest failed</Cell><Cell>Zadanie nie powiodło się</Cell></Row>
<Row><Cell>ui_questStarted</Cell><Cell>Quest started</Cell><Cell>Rozpoczęte zadanie</Cell></Row>
<Row><Cell>ui_reached_new_level</Cell><Cell>You've reached a new level in</Cell><Cell>Osiągnąłeś nowy poziom w:</Cell></Row>
<Row><Cell>ui_reached_new_level_female</Cell><Cell>You've achieved a new level in</Cell><Cell>Zyskałaś nowy poziom w</Cell></Row>
<Row><Cell>ui_rep_stolen_reputation</Cell><Cell>Reputation lowered</Cell><Cell>Obniżona Reputacja</Cell></Row>
<Row><Cell>ui_rep_stolen_sold</Cell><Cell>Stolen item sold!</Cell><Cell>Sprzedano kradziony przedmiot!</Cell></Row>
<Row><Cell>ui_rpg_CannotJumpWhileEncumbered</Cell><Cell>You can't jump while overloaded.</Cell><Cell>Nie możesz skakać, kiedy masz za dużo rzeczy.</Cell></Row>
<Row><Cell>ui_rpg_CannotSprintWhileEncumbered</Cell><Cell>You can't sprint while overloaded.</Cell><Cell>Nie możesz biec sprintem, jeżeli jesteś przeciążony.</Cell></Row>
<Row><Cell>ui_save_istvans_reinforcements</Cell><Cell>Save right before the battle in Q Istvan's Reinforcements</Cell><Cell>Zapisz grę tuż przed bitwą w Zadaniu „Odsiecz Istvana“.</Cell></Row>
<Row><Cell>ui_skill_too_low_to_repair_item</Cell><Cell>You don't have enough skill to repair this item.</Cell><Cell>Nie masz dość umiejętności, aby naprawić ten przedmiot.</Cell></Row>
<Row><Cell>ui_sleep</Cell><Cell>Sleep</Cell><Cell>Śpij</Cell></Row>
<Row><Cell>ui_south_shortcut</Cell><Cell>S</Cell><Cell>S</Cell></Row>
<Row><Cell>ui_southeast_shortcut</Cell><Cell>SE</Cell><Cell>SE</Cell></Row>
<Row><Cell>ui_southwest_shortcut</Cell><Cell>SW</Cell><Cell>SW</Cell></Row>
<Row><Cell>ui_use_armor</Cell><Cell>Put on armour</Cell><Cell>Weź tę zbroję</Cell></Row>
<Row><Cell>ui_use_burnherbs</Cell><Cell>Burn the herbs</Cell><Cell>Spal zioła</Cell></Row>
<Row><Cell>ui_use_fire</Cell><Cell>Deal with fire</Cell><Cell>Ogień</Cell></Row>
<Row><Cell>ui_use_chickenfeed</Cell><Cell>Feed chickens</Cell><Cell>Nakarm kury.</Cell></Row>
<Row><Cell>ui_use_item</Cell><Cell>Use</Cell><Cell>Użyj</Cell></Row>
<Row><Cell>ui_use_putherbs</Cell><Cell>Drop the herbs in</Cell><Cell>Wrzuć zioła do</Cell></Row>
<Row><Cell>ui_use_wash</Cell><Cell>Wash yourself</Cell><Cell>Umyj się</Cell></Row>
<Row><Cell>ui_west_shortcut</Cell><Cell>W</Cell><Cell>W</Cell></Row>
<Row><Cell>ui_you_gave</Cell><Cell>You parted with</Cell><Cell>Odstąpiłeś od</Cell></Row>
<Row><Cell>ui_you_gave_female</Cell><Cell>You parted with</Cell><Cell>Straciłaś</Cell></Row>
<Row><Cell>ui_you_got</Cell><Cell>You got</Cell><Cell>Otrzymałeś</Cell></Row>
<Row><Cell>ui_you_got_female</Cell><Cell>You got</Cell><Cell>Masz</Cell></Row>
<Row><Cell>ui_you_in_private_area</Cell><Cell>You're in a private area!</Cell><Cell>Jesteś na terenie prywatnym!</Cell></Row>
<Row><Cell>ui_you_tresspasing</Cell><Cell>You're trespassing!</Cell><Cell>Wkroczyłeś na czyjś teren!</Cell></Row>
<Row><Cell>UIA_COMBO</Cell><Cell>Combo</Cell><Cell>Kombinacje</Cell></Row>
<Row><Cell>UIA_KICK</Cell><Cell>Kick</Cell><Cell>Kopnij</Cell></Row>
<Row><Cell>UIA_PERFECT_BLOCK</Cell><Cell>Perfect block</Cell><Cell>Doskonały blok</Cell></Row>
<Row><Cell>UIA_PUNCH</Cell><Cell>Punch</Cell><Cell>Cios</Cell></Row>
<Row><Cell>UIA_RIPOSTE</Cell><Cell>Riposte</Cell><Cell>Riposta</Cell></Row>
<Row><Cell>USE_DOOR</Cell><Cell>Use door</Cell><Cell>Użyj drzwi</Cell></Row>
<Row><Cell>use_ladder</Cell><Cell>Use ladder</Cell><Cell>Użyj drabiny</Cell></Row>
<Row><Cell>waterTube_wash_max_text</Cell><Cell>You won't get any cleaner washing in a trough. For that you need the baths.</Cell><Cell>Tutaj już bardziej się nie domyjesz. Do tego potrzebujesz łaźni.</Cell></Row>
<Row><Cell>waterTube_wash_text</Cell><Cell>You've washed yourself as much as you can in a trough.</Cell><Cell>Umyłeś się w balii tak dokładnie, jak tylko się dało.</Cell></Row>
<Row><Cell>waterTube_wash_text_female</Cell><Cell>You've washed yourself all you can in a trough.</Cell><Cell>Umyłaś się w balii tak dokładnie, jak tylko się dało.</Cell></Row>
</Table>