<Table>
<Row><Cell>chapter1a_sch2_iRf2_e11_6IvY</Cell><Cell>The early 15th century was a time of turmoil in the Holy Roman Empire, which had flourished under the late Emperor Charles IV, but now, with his son Wenceslas “the Idle“ on the Bohemian throne, was falling into disarray.

</Cell><Cell>Varajane 15. sajand oli Saksa Rahvuse Püha Rooma keisririigis rahutu aeg. Keiser Karl IV oli pannud riigi õitsema, kuid nüüd tema trooni pärinud poeg Wenzel, keda hüüti ka "Joodikuks", häbistas mitte ainult ennast, kuid ka kogu Böömimaad.</Cell></Row>
<Row><Cell>chapter1a_sch2_iRf2_e12_U8N0</Cell><Cell>The King’s inactivity angered many of the nobility, as well as his half-brother, King Sigismund of Hungary, who decided to take drastic steps to restore order to the Empire…
</Cell><Cell>Kuninga passiivsus ja hoolimatus riigi suhtes ajas marru palju aadlikke, nagu ka tema poolvenna, Ungari kuninga Sigismundi, kes otsustas võtta trooni tagasi äärmuslike meetoditega.</Cell></Row>
<Row><Cell>chapter1a_sch2_iRf2_e12_vkUl</Cell><Cell>Silver Skalitz, 1403</Cell><Cell>Hõbeda Skalitz, 1403</Cell></Row>
<Row><Cell>chapter1a_sch7_9t19_e58_Suu4</Cell><Cell>In the castle.</Cell><Cell>Lossis.</Cell></Row>
<Row><Cell>chapter1a_sch7_9t19_e8_Zrcd</Cell><Cell>Run!</Cell><Cell>Jookse!</Cell></Row>
</Table>